[{"name":"mutual","trans":["adj. 共同的；相互的，彼此的"]},{"name":"similarity","trans":["n. 类似；相似点"]},{"name":"in need","trans":[" 在危难中；需要帮助的；在困难时"]},{"name":"find out","trans":["na. 查出；发现；看清…的面目；识破, 查明；找出；了解"]},{"name":"enhance","trans":["vt. 提高；加强；增加"]},{"name":"aspect","trans":["n. 方面；方向；形势；外貌"]},{"name":"emotional","trans":["adj. 情绪的；易激动的；感动人的"]},{"name":"overall","trans":["adj. 全部的；全体的；一切在内的,adv. 全部地；总的说来,n. 工装裤；罩衫"]},{"name":"reward","trans":["n.  报酬；报答；酬谢,vt.  奖励；奖赏"]},{"name":"frustrate","trans":["vt. 挫败；阻挠；使感到灰心,adj. 挫败的；无益的,vi. 失败；受挫"]},{"name":"romantic","trans":["n. 浪漫的人,adj. 浪漫的；多情的；空想的,vt. 使…浪漫化"]},{"name":"household","trans":["n. 全家人，一家人；(包括佣工在内的)家庭，户,adj. 家庭的；日常的；王室的"]},{"name":"consist","trans":["vi. 由…组成；在于；符合"]},{"name":"abrupt","trans":["adj. 生硬的；突然的；唐突的；陡峭的"]},{"name":"unresolved","trans":["adj. 未解决的；无决断力的；不果断的"]},{"name":"issue","trans":["n. 问题；流出；期号；发行物,vt. 发行，发布；发给；放出，排出,vi. 发行；流出；造成…结果；传下"]},{"name":"recognize","trans":["vt. 认出，识别；承认,vi. 确认，承认；具结"]},{"name":"compromise","trans":["n. 妥协，和解；折衷,vt. 妥协；危害,vi. 妥协；让步"]},{"name":"willingness","trans":["n. 乐意；心甘情愿；自动自发"]},{"name":"resolve","trans":["n. 坚决；决定要做的事,vt. 决定；溶解；使…分解；决心要做…,vi. 解决；决心；分解"]},{"name":"assess","trans":["vt. 评定；估价；对…征税"]},{"name":"misconception","trans":["n. 误解；错觉；错误想法"]},{"name":"prevent","trans":["vt. 预防，防止；阻止,vi. 妨碍，阻止"]},{"name":"burn out","trans":["na. 烧起来；烧光；烧尽；烧断, 烧掉；烧坏；熄灭"]},{"name":"consist of","trans":["v. 由…合成, 由……组成；由…构成；包括"]},{"name":"due to","trans":["un. 由于；预定；因为；亏, 应归于；由於；由…引起"]},{"name":"prevent sb. from doing sth.","trans":["找不到解释"]},{"name":"pray","trans":["vi. 祈祷；请；恳求,vt. 祈祷；恳求；央求"]},{"name":"panic","trans":["n. 恐慌，惊慌；大恐慌,adj. 恐慌的；没有理由的,vt. 使恐慌,vi. 十分惊慌"]},{"name":"shabby","trans":["adj. 破旧的；卑鄙的；吝啬的；低劣的"]},{"name":"noisy","trans":["adj. .嘈杂的；喧闹的；聒噪的"]},{"name":"relative","trans":["n. 亲戚；相关物； 关系词；亲缘植物,adj. 相对的；有关系的；成比例的"]},{"name":"abundant","trans":["adj. 丰富的；充裕的；盛产"]},{"name":"disappointment","trans":["n. 失望；沮丧"]},{"name":"lick","trans":["vt. 舔；卷过；鞭打,vt. （非正式）战胜,vi. 舔；轻轻拍打,n. 舔；打；少许"]},{"name":"chopstick","trans":["n. 筷子"]},{"name":"murmur","trans":["n. 低语；低语声；低声抱怨；潺潺声,vi. 低声说；私下抱怨；发出轻柔持续的声音,vt. 低声说"]},{"name":"steam","trans":["n. 蒸汽；精力,adj. 蒸汽的,vt. 蒸，散发；用蒸汽处理,vi. 蒸，冒水汽"]},{"name":"tender","trans":["n. 偿付，清偿；看管人；小船,adj. 温柔的；柔软的；脆弱的；幼稚的；难对付的,vt. 提供，偿还；使…变嫩；使…变柔软,vi. 投标；变柔软"]},{"name":"cheek","trans":["n. 面颊，脸颊；臀部,vt. 无礼地向…讲话，对…大胆无礼"]},{"name":"lean","trans":["vi. 倾斜；倚靠；倾向；依赖,adj. 瘦的；贫乏的，歉收的,vt. 使倾斜,n. 瘦肉；倾斜；倾斜度"]},{"name":"burp","trans":["n. 打嗝；饱嗝儿,vt. 使打嗝,vi. 打嗝；打饱嗝"]},{"name":"reddish","trans":["adj. 微红的；略带红色的"]},{"name":"inevitable","trans":["adj. 必然的，不可避免的"]},{"name":"clash","trans":["n. 冲突，不协调；碰撞声，铿锵声,vt. 使碰撞作声,vi. 冲突，抵触；砰地相碰撞，发出铿锵声"]},{"name":"phenomenon","trans":["n. 现象；奇迹；杰出的人才"]},{"name":"enrich","trans":["vt. 使充实；使肥沃；使富足"]},{"name":"metaphorically","trans":["adv. 隐喻地；用比喻"]},{"name":"digest","trans":["n. 文摘；摘要,vt. 消化；吸收；融会贯通,vi. 消化"]},{"name":"eliminate","trans":["vt. 消除；排除"]},{"name":"discard","trans":["n. 抛弃；被丢弃的东西或人,vt. 抛弃；放弃；丢弃,vi. 放弃"]},{"name":"dross","trans":["n. 渣滓；浮渣；碎屑"]},{"name":"imitation","trans":["n. 模仿，仿造；仿制品,adj. 人造的，仿制的"]},{"name":"equivalent","trans":["n. 等价物，相等物,adj. 等价的，相等的；同意义的"]},{"name":"novelty","trans":["n. 新奇；新奇的事物；新颖小巧而廉价的物品"]},{"name":"originality","trans":["n. 创意；独创性，创造力；原始；新奇"]},{"name":"artistry","trans":["n. 艺术性；工艺；艺术技巧；艺术效果；艺术工作"]},{"name":"by no means","trans":["na. 决不；并没有, 一点也不；绝不；无论如何决不"]},{"name":"on the contrary","trans":["na. 反之, 正相反；相反地；相反的"]},{"name":"ethnic","trans":["adj. 种族的；人种的"]},{"name":"consequently","trans":["adv. 因此；结果；所以"]},{"name":"memorable","trans":["adj. 显著的，难忘的；值得纪念的"]},{"name":"portable","trans":["n. 手提式打字机,adj. 手提的，便携式的；轻便的"]},{"name":"bribe","trans":["n. 贿赂,vt. 贿赂，收买,vi. 行贿"]},{"name":"presentable","trans":["adj. 漂亮的；可见人的；有规矩的"]},{"name":"discrete","trans":["n. 分立元件；独立部件,adj. 离散的，不连续的"]},{"name":"improvise","trans":["vt. 即兴创作；即兴表演；临时做；临时提供,vi. 即兴创作；即兴表演；临时凑合"]},{"name":"discourage","trans":["vt. 阻止；使气馁"]},{"name":"tempt","trans":["vt. 诱惑；引起；冒…的风险；使感兴趣"]},{"name":"insurance","trans":["n. 保险；保险费；保险契约；赔偿金"]},{"name":"physical","trans":["n. 体格检查,adj.  物理的；身体的；物质的；根据自然规律的，符合自然法则的"]},{"name":"alter","trans":["vt. 改变，更改,vi. 改变；修改"]},{"name":"transform","trans":["vt. 改变，使…变形；转换,vi. 变换，改变；转化"]},{"name":"prairie","trans":["n. 大草原；牧场"]},{"name":"reservoir","trans":["n. 水库；蓄水池"]},{"name":"irrigation","trans":["n. 灌溉； 冲洗；冲洗法"]},{"name":"hydroelectric","trans":["adj. 水力发电的；水电治疗的"]},{"name":"modify","trans":["vt. 修改，修饰；更改,vi. 修改"]},{"name":"drain","trans":["n. 排水；下水道，排水管；消耗,vt. 喝光，耗尽；使流出；排掉水,vi. 排水；流干"]},{"name":"marsh","trans":["n. 沼泽；湿地,adj. 沼泽的；生长在沼泽地的"]},{"name":"beneficial","trans":["adj. 有益的，有利的；可享利益的"]},{"name":"exhaust","trans":["n. 排气；废气；排气装置,vt. 排出；耗尽；使精疲力尽；彻底探讨,vi. 排气"]},{"name":"industrialized","trans":["adj. 工业化的,v. 使工业化；将…组成产业（industrialize的过去分词）"]},{"name":"pressing","trans":["n. 压；冲压件,v. 压；按；熨烫衣物（press的ing形式）,adj. 紧迫的；迫切的；恳切的"]},{"name":"massive","trans":["adj. 大量的；巨大的，厚重的；魁伟的"]},{"name":"negative","trans":["adj.  负的；消极的；否定的；阴性的,n. 否定；负数； 底片,vt. 否定；拒绝"]},{"name":"indifference","trans":["n. 漠不关心；冷淡；不重视；中立"]},{"name":"suicide","trans":["n. 自杀；自杀行为；自杀者,adj. 自杀的,vt. 自杀,vi. 自杀"]},{"name":"conserve","trans":["n. 果酱；蜜饯,vt. 保存；将…做成蜜饯；使守恒"]},{"name":"cut through","trans":["v. 洞穿, 穿过；直通式；穿透"]},{"name":"bring about","trans":["na. 造成；带来；(使船)回转, 引起；导致；产生"]},{"name":"suffer from","trans":[" 患（某种病），受（某种病痛）折磨; 因…而受罚; 闹; 罹"]},{"name":"lack of","trans":["v. 缺乏, 缺少；不足；不够"]},{"name":"urbanization","trans":["n. 都市化；文雅化"]},{"name":"release","trans":["n. 释放；发布；让与,vt. 释放；发射；让与；允许发表"]},{"name":"decline","trans":["n. 下降；衰退；斜面,vt. 谢绝；婉拒,vi. 下降；衰落；谢绝"]},{"name":"metropolis","trans":["n. 大都市；首府；重要中心"]},{"name":"respectively","trans":["adv. 分别地；各自地，独自地"]},{"name":"pose","trans":["vi. 摆姿势；佯装；矫揉造作,vt. 造成，形成；摆姿势；装模作样；提出…讨论,n. 姿势，姿态；装模作样"]},{"name":"dynamism","trans":["n. 活力；动态；物力论；推动力；精神动力作用"]},{"name":"acquaint","trans":["vt. 使熟悉；使认识"]},{"name":"representative","trans":["n. 代表；典型；众议员,adj. 典型的，有代表性的；代议制的"]},{"name":"reception","trans":["n. 接待；接收；招待会；感受；反应"]},{"name":"management","trans":["n. 管理；管理人员；管理部门；操纵；经营手段"]},{"name":"copy","trans":["n. 副本；一册；摹仿,vt. 复制；复印；抄袭,vi. 复制；复印；抄袭"]},{"name":"cubicle","trans":["n. 小卧室；小隔间"]},{"name":"get acquainted with","trans":["na. 熟知；与…相识, 熟悉；了解；开始知道"]},{"name":"show ... around","trans":["v. 带…参观, 带……参观；四处参观；领…参观"]},{"name":"pinch","trans":["n. 匮乏；少量；夹痛,vt. 捏；勒索；使苦恼；掐掉某物，修剪,vi. 夹痛；节省"]},{"name":"sweltering","trans":["adj. 闷热的；热得难受的"]},{"name":"rent","trans":["n. 租金,vt. 出租；租用；租借,vi. 租；出租"]},{"name":"necessity","trans":["n. 需要；必然性；必需品"]},{"name":"budget","trans":["n. 预算，预算费,adj. 廉价的,vt. 安排，预定；把…编入预算,vi. 编预算，做预算"]},{"name":"consultant","trans":["n. 顾问；咨询者；会诊医生"]},{"name":"hash","trans":["n. 剁碎的食物；混杂，拼凑；重新表述,vt. 搞糟，把…弄乱；切细；推敲"]},{"name":"booming","trans":["adj. 兴旺的，繁荣的；大受欢迎的,v. 兴旺（boom的ing形式）；发出隆隆声"]},{"name":"expenditure","trans":["n. 支出，花费；经费，消费额"]},{"name":"accessory","trans":["n. 配件；附件； 从犯,adj. 副的；同谋的；附属的"]},{"name":"complain about","trans":["v. 埋怨, 抱怨；抱怨某事；抱怨某人或事情"]},{"name":"make ends meet","trans":[" 使收支相抵；量入为出；收支平衡"]},{"name":"set aside","trans":["na. 搁置；拨出；驳回, 留出；取消；挑出，留出"]},{"name":"hash house","trans":["na. 廉价小餐馆, 廉价餐馆；经济餐馆；军队中的餐厅"]},{"name":"in spite of","trans":["na. spite of 不管；无视, 尽管；不顾；虽然"]},{"name":"depend on","trans":["v. 依靠, 依赖；取决于；视……而定"]},{"name":"statistic","trans":["n. 统计数值,adj. 统计的，统计学的"]},{"name":"oversupply","trans":["n.  供给过多；过多的供应品,vt. 过度供给"]},{"name":"aerospace","trans":["n. 航空宇宙； 航空航天空间"]},{"name":"specialist","trans":["n. 专家；专门医师,adj. 专家的；专业的"]},{"name":"temporary","trans":["n. 临时工，临时雇员,adj. 暂时的，临时的"]},{"name":"carpenter","trans":["n. 木匠，木工,vt. 制作,vi. 当木匠，做木匠工作"]},{"name":"mechanic","trans":["n. 技工，机修工,adj. 手工的"]},{"name":"plumber","trans":["n. 水管工；堵漏人员"]},{"name":"prosperous","trans":["adj. 繁荣的；兴旺的"]},{"name":"myth","trans":["n. 神话；虚构的人，虚构的事"]},{"name":"indoctrinate","trans":["vt. 灌输；教导"]},{"name":"enrollment","trans":["n. 登记；入伍"]},{"name":"moblog","trans":[" 移动博客"]},{"name":"combination","trans":["n. 结合；组合；联合； 化合"]},{"name":"publish","trans":["vi. 出版；发行；刊印,vt. 出版；发表；公布"]},{"name":"entry","trans":["n. 进入；入口；条目；登记；报关手续；对土地的侵占"]},{"name":"device","trans":["n. 装置；策略；图案"]},{"name":"especially","trans":["adv. 特别；尤其；格外"]},{"name":"laptop","trans":["n. 膝上型轻便电脑，笔记本电脑"]},{"name":"edit","trans":["vt. 编辑；校订,n. 编辑工作"]},{"name":"browser","trans":["n.  浏览器；吃嫩叶的动物；浏览书本的人"]},{"name":"shoot","trans":["n. 射击；摄影；狩猎；急流,vt. 射击，射中；拍摄；发芽；使爆炸；给…注射,vi. 射击；发芽；拍电影"]},{"name":"image","trans":["n. 影像；想象；肖像；偶像,vt. 想象；反映；象征；作…的像"]},{"name":"upload","trans":["vt. 上传"]},{"name":"description","trans":["n. 描述，描写；类型；说明书"]},{"name":"on the move","trans":["na. 一直在动；开始活动；(事件)正在发展；动着, 在活动中；移动中；在移动中"]},{"name":"on a business trip","trans":[" 出差；出差旅行；因公出差"]},{"name":"happen to do sth.","trans":["找不到解释"]},{"name":"multi-functional","trans":["adj. 多功能的"]},{"name":"application","trans":["n. 应用；申请；应用程序；敷用"]},{"name":"corporation","trans":["n. 公司；法人（团体）；社团；大腹便便；市政当局"]},{"name":"combine","trans":["n. 联合收割机；联合企业,vt. 使化合；使联合，使结合,vi. 联合，结合；化合"]},{"name":"function","trans":["n. 功能； 函数；职责；盛大的集会,vi. 运行；活动；行使职责"]},{"name":"cost-effective","trans":["adj. 划算的；成本效益好的（等于cost-efficient）"]},{"name":"contact","trans":["n. 接触，联系,vt. 使接触，联系,vi. 使接触，联系"]},{"name":"connection","trans":["n. 连接；关系；人脉；连接件"]},{"name":"access","trans":["n. 进入；使用权；通路,vt. 使用；存取；接近"]},{"name":"gradual","trans":["n. 弥撒升阶圣歌集,adj. 逐渐的；平缓的"]},{"name":"compare","trans":["vi. 相比，匹敌；比较，区别；比拟（常与to连用）,vt. 比拟，喻为；构成,n. 比较"]},{"name":"format","trans":["n. 格式；版式；开本,vt. 使格式化；规定…的格式,vi. 设计版式"]},{"name":"publicly","trans":["adv. 公然地；以公众名义"]},{"name":"vicinity","trans":["n. 邻近，附近；近处"]},{"name":"respond","trans":["n. 应答；唱和,vi. 回答；作出反应；承担责任,vt. 以…回答"]},{"name":"brand","trans":["n. 商标，牌子；烙印,vt. 铭刻于，铭记；打烙印于；印…商标于"]},{"name":"account","trans":["n. 账户；解释；账目，账单；理由；描述,vt. 认为；把…视为,vi. 解释；导致；报账"]},{"name":"target","trans":["n. 目标；靶子,vt. 把……作为目标；规定……的指标；瞄准某物"]},{"name":"consumer","trans":["n. 消费者；用户，顾客"]},{"name":"interaction","trans":["n. 相互作用； 交互作用,n. 互动"]},{"name":"promotional","trans":["adj. 促销的；增进的；奖励的"]},{"name":"randomly","trans":["adv. 随便地，任意地；无目的地，胡乱地；未加计划地"]},{"name":"automatically","trans":["adj. 不经思索的,adv. 自动地；机械地；无意识地"]},{"name":"conclude","trans":["vi. 推断；断定；决定,vt. 推断；决定，作结论；结束"]},{"name":"vivid","trans":["adj. 生动的；鲜明的；鲜艳的"]},{"name":"expand","trans":["vt. 扩张；使膨胀；详述,vi. 发展；张开，展开"]},{"name":"build up","trans":["na. 同“build”；建立；复兴；集结(部队), 逐步建立；增进；积累"]},{"name":"get access to","trans":["可以到达；可以使用；有接触(或进入、使用)的机会(或权利)"]},{"name":"hook","trans":["n. 挂钩，吊钩,vt. 钩住；引上钩,vi. 钩住；弯成钩状"]},{"name":"symptom","trans":["n.  症状；征兆"]},{"name":"drug","trans":["n. 药；毒品；麻醉药；滞销货,vt. 使服麻醉药；使服毒品；掺麻醉药于,vi. 吸毒"]},{"name":"alcohol","trans":["n. 酒精，乙醇"]},{"name":"addiction","trans":["n. 上瘾，沉溺；癖嗜"]},{"name":"withdrawal","trans":["n. 撤退，收回；提款；取消；退股"]},{"name":"craving","trans":["n. 渴望；热望,v. 渴望；恳求（crave的ing形式）"]},{"name":"anxiety","trans":["n. 焦虑；渴望；挂念；令人焦虑的事"]},{"name":"inability","trans":["n. 无能力；无才能"]},{"name":"equate","trans":["vt. 使相等；视为平等,vi. 等同"]},{"name":"disorder","trans":["n. 混乱；骚乱,vt. 使失调；扰乱"]},{"name":"allegedly","trans":["adv. 依其申述；据说，据称"]},{"name":"malnutrition","trans":["n. 营养失调，营养不良"]},{"name":"virtual","trans":["adj.  虚拟的；实质上的，事实上的（但未在名义上或正式获承认）"]},{"name":"casual","trans":["n. 便装；临时工人；待命士兵,adj. 随便的；非正式的；临时的；偶然的"]},{"name":"rarely","trans":["adv. 很少地；难得；罕有地"]},{"name":"loyalty","trans":["n. 忠诚；忠心；忠实；忠于…感情"]},{"name":"outlet","trans":["n. 出口，排放孔； 电源插座；销路；发泄的方法；批发商店"]},{"name":"celebration","trans":["n. 庆典，庆祝会；庆祝；颂扬"]},{"name":"schedule","trans":["n. 时间表；计划表；一览表,vt. 安排，计划；编制目录；将……列入计划表"]},{"name":"packed","trans":["adj. （常用来构成复合词）充满…的，塞满了…的,v.  包装（pack的过去分词）"]},{"name":"celebrate","trans":["vt. 庆祝；举行；赞美；祝贺；宣告,vi. 庆祝；过节；举行宗教仪式"]},{"name":"have in mind","trans":["na. 记住；铭记不忘；注意, 考虑到；想到；记得"]},{"name":"apply for","trans":["v. 寻求；申请, 提出申请；申请…职位；请求"]},{"name":"stop by","trans":["na. 顺便到(某处)访问；同“stop off”, 顺便到访问；顺便拜访；顺便访问"]},{"name":"capacity","trans":["n. 能力；容量；资格，地位；生产力"]},{"name":"creative","trans":["adj. 创造性的"]},{"name":"productive","trans":["adj. 能生产的；生产的，生产性的；多产的；富有成效的"]},{"name":"authentically","trans":["adv. 真正地，确实地；可靠地"]},{"name":"credible","trans":["adj. 可靠的，可信的"]},{"name":"trustworthy","trans":["adj. 可靠的；可信赖的"]},{"name":"genuine","trans":["adj. 真实的，真正的；诚恳的"]},{"name":"separate","trans":["n. .分开；抽印本,adj. 单独的；分开的；不同的；各自的；,vt. 使分离；使分开；使分居,vi. 分开；隔开；分居"]},{"name":"evaluate","trans":["vt. 评价；估价；求…的值,vi. 评价；估价"]},{"name":"admire","trans":["vt. 钦佩；赞美,vi. 钦佩；称赞"]},{"name":"demolish","trans":["vt. 拆除；破坏；毁坏；推翻；驳倒"]},{"name":"bound","trans":["n. 范围；跳跃,adj. 有义务的；必定的；受约束的；装有封面的,vt. 束缚；使跳跃,vi. 限制；弹起"]},{"name":"awe","trans":["n. 敬畏,vt. 使敬畏；使畏怯"]},{"name":"preserve","trans":["n. 保护区；禁猎地；加工成的食品,vt. 保存；保护；维持；腌；禁猎"]},{"name":"dignity","trans":["n. 尊严；高贵"]},{"name":"postpone","trans":["vt. 使…延期；把…放在次要地位；把…放在后面,vi. 延缓，延迟；延缓发作"]},{"name":"discipline","trans":["n. 学科；纪律；训练；惩罚,vt. 训练，训导；惩戒"]},{"name":"isolate","trans":["n.  隔离种群,vt. 使隔离；使孤立；使绝缘,adj. 隔离的；孤立的,vi. 隔离；孤立"]},{"name":"compassionate","trans":["adj. 慈悲的；富于同情心的,vt. 同情；怜悯"]},{"name":"committed","trans":["v. 承诺；委托；干坏事；付诸（commit的过去分词）,adj. 坚定的；效忠的；承担义务的"]},{"name":"adversity","trans":["n. 逆境；不幸；灾难；灾祸"]},{"name":"separate ... from ...","trans":["找不到解释"]},{"name":"pretend to do sth.","trans":["找不到解释"]},{"name":"come to conclusion","trans":["找不到解释"]},{"name":"go after","trans":["na. 追求, 追逐；追赶；寻找"]},{"name":"isolate from ...","trans":["找不到解释"]},{"name":"irrelevant","trans":["adj. 不相干的；不切题的"]},{"name":"industry","trans":["n. 产业；工业；勤勉"]},{"name":"enticing","trans":["v. 引诱；诱骗（entice的ing形式）,adj. 迷人的；引诱的"]},{"name":"upward","trans":["adj. 向上的；上升的,adv. 向上"]},{"name":"spiral","trans":["n. 螺旋；旋涡；螺旋形之物,adj. 螺旋形的；盘旋的,vt. 使成螺旋形；使作螺旋形上升,vi. 盘旋；成螺旋形；螺旋形上升（过去式spiraled\/spiralled，过去分词spiraled\/spiralled，现在分词spiraling\/spiralling，第三人称单数spirals，副词spirally）"]},{"name":"transportable","trans":["n. 便携式电视机；便携式计算机,adj. 可运输的；便携式的"]},{"name":"bias","trans":["n. 偏见；偏爱；斜纹；乖离率,adj. 偏斜的,vt. 使存偏见,adv. 偏斜地"]},{"name":"incline","trans":["n. 倾斜；斜面；斜坡,vt. 使倾斜；使倾向于,vi. 倾斜；倾向；易于"]},{"name":"troublesome","trans":["adj. 麻烦的；讨厌的；使人苦恼的"]},{"name":"scenario","trans":["n. 方案；情节；剧本；设想"]},{"name":"prohibitively","trans":["adv. 禁止地；过高地；过分地"]},{"name":"establish","trans":["vi. 植物定植,vt. 建立；创办；安置"]},{"name":"evil","trans":["n. 罪恶，邪恶；不幸,adj. 邪恶的；不幸的；有害的；讨厌的"]},{"name":"aged","trans":["v. 老化（age的过去式）；成熟；变老,adj. 年老的；…岁的；老年人特有的"]},{"name":"maintain","trans":["vt. 维持；继续；维修；主张；供养"]},{"name":"facility","trans":["n. 设施；设备；容易；灵巧"]},{"name":"nursing home","trans":["n. 小型私立疗养院；（尤指）私立养老院, 护理之家；护理院；老人院"]},{"name":"a heavy burden","trans":["找不到解释"]},{"name":"care for","trans":["v. 照顾；关心；喜欢, 照料；关怀；照管"]},{"name":"professional care","trans":[" 专业小心；专业的照顾；专业护理"]},{"name":"finding","trans":["n. 发现；裁决；发现物,v. 找到；感到（find的ing形式）；遇到"]},{"name":"question","trans":["n. 问题，疑问；询问；疑问句,vt. 询问；怀疑；审问,vi. 询问；怀疑；审问"]},{"name":"researcher","trans":["n. 研究员"]},{"name":"emotion","trans":["n. 情感；情绪"]},{"name":"mental","trans":["adj. 精神的；脑力的；疯的,n. 精神病患者"]},{"name":"tension","trans":["n. 张力，拉力；紧张，不安；电压,vt. 使紧张；使拉紧"]},{"name":"sharply","trans":["adv. 急剧地；锐利地"]},{"name":"pattern","trans":["n. 模式；图案；样品,vt. 模仿；以图案装饰,vi. 形成图案"]},{"name":"unemployed","trans":["adj. 失业的；未被利用的"]},{"name":"well-being","trans":["n. 幸福；康乐"]},{"name":"emotional pattern","trans":["《英汉医学词典》emotional pattern,情绪型"]},{"name":"brain chemistry","trans":[" 脑化学；脑部化学；脑化学变化"]},{"name":"psychologically","trans":["adv. 心理上地；心理学地"]},{"name":"guard","trans":["n. 守卫；警戒；护卫队；防护装置,vi. 警惕,vt. 保卫；监视"]},{"name":"absorption","trans":["n. 吸收；全神贯注，专心致志"]},{"name":"direct","trans":["adj. 直接的；直系的；亲身的；恰好的,vt. 管理；指挥；导演；指向,adv. 直接地；正好；按直系关系,vi. 指导；指挥"]},{"name":"keen","trans":["adj. 敏锐的，敏捷的；渴望的；强烈的；热心的；锐利的,n. 痛哭，挽歌"]},{"name":"cling","trans":["vi. 坚持，墨守；紧贴；附着"]},{"name":"vigor","trans":["n.  活力，精力"]},{"name":"vitality","trans":["n. 活力，生气；生命力，生动性"]},{"name":"indifferent","trans":["adj. 漠不关心的；无关紧要的；中性的，中立的"]},{"name":"infancy","trans":["n. 初期；婴儿期；幼年"]},{"name":"impersonal","trans":["n. 非人称动词；不具人格的事物,adj. 客观的；非个人的；没有人情味的；非人称的"]},{"name":"essential","trans":["n. 本质；要素；要点；必需品,adj. 基本的；必要的；本质的；精华的"]},{"name":"incapable","trans":["adj. 不能的；无能力的；不能胜任的"]},{"name":"good old days","trans":[" 美好旧时光；美好的往日；当年"]},{"name":"cling to","trans":["v. 依附；坚持, 墨守；紧紧抓住；附着"]},{"name":"be indifferent to","trans":["na. 对…不关心, 不在乎；对…漠不关心；对……感到无所谓"]},{"name":"owing to","trans":["conj. 由于；因为,prep. 因为；由于, 归因于；由于…的原因；多亏"]},{"name":"in this sense","trans":["找不到解释"]},{"name":"be incapable of","trans":["v. 无能力, 不会；不能；没有能力做"]},{"name":"fierce","trans":["adj. 凶猛的；猛烈的；暴躁的"]},{"name":"stable","trans":["n. 马厩；牛棚,adj. 稳定的；牢固的；坚定的,vt. 赶入马房,vi. 被关在马厩"]},{"name":"unlimited","trans":["adj. 无限制的；无限量的；无条件的"]},{"name":"creativity","trans":["n. 创造力；创造性"]},{"name":"eloquent","trans":["adj. 意味深长的；雄辩的，有口才的；有说服力的；动人的"]},{"name":"stable income","trans":["找不到解释"]},{"name":"dreamer","trans":["n. 梦想家；做梦的人；不切实际的人"]},{"name":"doer","trans":["n. 实干家；行为者"]},{"name":"stuff","trans":["n. 东西；材料；填充物；素材资料,vt. 塞满；填塞；让吃饱,vi. 吃得过多"]},{"name":"execute","trans":["vt. 实行；执行；处死"]},{"name":"vision","trans":["n. 视力；美景；眼力；幻象；想象力；幻视（漫威漫画旗下超级英雄）,vt. 想象；显现；梦见"]},{"name":"organized","trans":["adj. 有组织的；安排有秩序的；做事有条理的,v. 组织（organize的过去分词）"]},{"name":"systematically","trans":["adv. 有系统地；有组织地"]},{"name":"critically","trans":["adv. 精密地；危急地；严重地；批评性地；用钻研眼光地；很大程度上；极为重要地"]},{"name":"crush","trans":["n. 粉碎；迷恋；压榨；拥挤的人群,vt. 压碎；弄皱，变形；使…挤入,vi. 挤；被压碎"]},{"name":"label","trans":["vt. 标注；贴标签于,n. 标签；商标；签条"]},{"name":"folder","trans":["n. 文件夹；折叠机；折叠式印刷品"]},{"name":"restructure","trans":["vt. 调整；重建；更改结构"]},{"name":"nerd","trans":["n. 呆子；书呆子；讨厌的人"]},{"name":"mask","trans":["n. 面具；口罩；掩饰,vi. 掩饰；戴面具；化装,vt. 掩饰；戴面具；使模糊"]},{"name":"take action","trans":["na. 动手；采取行动；采取(快速)措施；提起诉讼, 行动起来；采取措施；实施行动"]},{"name":"file management system","trans":["un. 文件管理系统, 档案管理系统；支持文件管理系统"]},{"name":"berry","trans":["n. 浆果（葡萄，番茄等）,vi. 采集浆果"]},{"name":"blackberry","trans":["n.  黑莓"]},{"name":"pasture","trans":["n. 草地；牧场；牧草,vt. 放牧；吃草"]},{"name":"quart","trans":["n. 夸脱（容量单位）；一夸脱的容器"]},{"name":"slate","trans":["n. 板岩；石板；蓝色；石片,adj. 板岩的；石板色的,vt. 铺石板；严厉批评某人；计划"]},{"name":"figure","trans":["n. 数字；人物；图形；价格；（人的）体形；画像,vt. 计算；认为；描绘；象征,vi. 计算；出现；扮演角色"]},{"name":"measure","trans":["n. 测量；措施；程度；尺寸,vt. 测量；估量；权衡,vi. 测量；估量"]},{"name":"develop a habit of ...","trans":["找不到解释"]},{"name":"at the thought of ...","trans":["找不到解释"]}]