[{"name":"straight","trans":["n. 直；直线；直男，直女，异性恋者,adj. 直的；连续的；笔直的；正直的；整齐的；异性恋的,adv. 直接地；不断地；立即；坦率地"]},{"name":"go straight on","trans":["v. 一直走, 直着走；径直往前走；笔直走"]},{"name":"left","trans":["adj. 左边的；左派的；剩下的,adv. 在左面,n. 左边；左派；激进分子,v. 离开（leave的过去式）"]},{"name":"right","trans":["n. 正确；右边；正义,adj. 正确的；直接的；右方的,vt. 纠正,adv. 正确地；恰当地；彻底地,vi. 复正；恢复平稳"]},{"name":"lost","trans":["adj. 失去的；丧失的；迷惑的,v. 遗失（lose的过去分词）；失败"]},{"name":"live","trans":["adj. 活的；生动的；实况转播的；精力充沛的,vt. 经历；度过,vi. 活；居住；生存"]},{"name":"No.","trans":["找不到解释"]},{"name":"number","trans":["n. 数；（杂志等的）期；号码；数字；算术,vi. 计入；总数达到,vt. 编号；计入；数…的数目；使为数有限"]},{"name":"street","trans":["n. 街道,adj. 街道的"]},{"name":"excuse me","trans":["un. 请原谅；对不起, 劳驾；打扰一下；打扰了"]},{"name":"turn left","trans":["un. 向左转, 转左；向左走；向左拐"]},{"name":"turn right","trans":["na. 转往右面, 向右转；向右拐；转右"]},{"name":"next to","trans":["prep. 紧邻；在…近旁；仅次于；紧接, 在…旁边；紧挨着；与……相邻"]},{"name":"supermarket","trans":["n. 超级市场；自助售货商店"]},{"name":"beside","trans":["prep. 在旁边；与…相比；和…无关"]},{"name":"cinema","trans":["n. 电影；电影院；电影业，电影制作术"]},{"name":"so much","trans":["na. 和…一样多；就只那么多；多少, 非常；这么多；如此多"]},{"name":"You're welcome!","trans":["找不到解释"]},{"name":"station","trans":["n. 车站；驻地；地位；身份,vt. 配置；安置；驻扎"]},{"name":"train","trans":["n. 火车；行列；长队；裙裾,v. 培养；训练；瞄准"]},{"name":"hill","trans":["n. 小山；丘陵；斜坡；山冈"]},{"name":"near","trans":["adj. 近的；亲近的；近似的,adv. 近；接近,prep. 靠近；近似于"]},{"name":"house","trans":["n. 住宅；家庭；机构；议会；某种用途的建筑物,vt. 覆盖；给…房子住；把…储藏在房内,vi. 住"]},{"name":"read","trans":["n. 阅读；读物,adj. 有学问的,vi. 读；读起来,vt. 阅读；读懂，理解"]},{"name":"running","trans":["n. 运转；赛跑；流出,v. 跑；运转（run的ing形式）；行驶,adj. 连续的；流动的；跑着的；运转着的"]},{"name":"these","trans":["adj. 这些的,pron. 这些"]},{"name":"picture","trans":["n. 照片，图画；影片；景色；化身,vt. 画；想像；描写"]},{"name":"take","trans":["vi. 拿；获得,vt. 拿，取；采取；接受（礼物等）；买，花费；耗费（时间等）,n. 捕获量；看法；利益，盈益；（入场券的）售得金额"]},{"name":"take pictures","trans":[" 照相；拍照；拍照片"]},{"name":"children","trans":["n. 孩子们（child的复数）"]},{"name":"child","trans":["n. 儿童，小孩，孩子；产物；子孙；幼稚的人；弟子"]},{"name":"listen","trans":["vi. 听，倾听；听从，听信,n. 听，倾听"]},{"name":"listen to","trans":["v. 听, 倾听；收听；听从"]},{"name":"talk","trans":["n. 谈话；演讲；空谈,vi. 谈话；说闲话,vt. 说；谈话；讨论"]},{"name":"talk to","trans":["na. 向…谈；申斥, 责备；与…谈话；和……交谈"]},{"name":"China","trans":["n. 中国,n. china，瓷器,adj. 中国的；中国制造的,adj. china，瓷制的"]},{"name":"kid","trans":["n. 小孩；小山羊,vt. 欺骗；取笑；戏弄,vi. 欺骗；取笑；戏弄,adj. 小山羊皮制的；较年幼的"]},{"name":"get on","trans":["na. 上马；安上；过日子；相投 (with together), 上车；进展；相处"]},{"name":"can","trans":["aux. 能； 能够； 可以； 可能,n. 罐头； （用金属或塑料制作的）容器； （马口铁或其他金属制作的）食品罐头,vt. 将…装入密封罐中保存"]},{"name":"see","trans":["vi. 看；看见；领会,vt. 看见；理解；领会"]},{"name":"lots of","trans":["adj. 许多；很多, 大量；大量的；许多的"]},{"name":"interesting","trans":["adj. 有趣的；引起兴趣的，令人关注的"]},{"name":"thing","trans":["n. 事情；东西；事物；情况"]},{"name":"people","trans":["n. 人；人类；民族；公民,vt. 居住于；使住满人"]},{"name":"row","trans":["n. 行，排；划船；街道；吵闹,vt. 划船；使……成排,vi. 划船；争吵"]},{"name":"dragon","trans":["n. 龙；凶暴的人，凶恶的人；严厉而有警觉性的女人"]},{"name":"boat","trans":["n. 小船；轮船,vi. 划船"]},{"name":"dragon boat","trans":["n. 龙舟；龙船, 赛龙舟；龙舟赛；划龙舟"]},{"name":"men","trans":["n. 男人，人类（man的复数）"]},{"name":"man","trans":["n. 人；男人；人类；丈夫；雇工,vt. 操纵；给…配置人员；使增强勇气；在…就位"]},{"name":"between","trans":["prep. 在…之间,adv. 在中间"]},{"name":"chess","trans":["n. 国际象棋，西洋棋"]},{"name":"play chess","trans":["na. 下象棋, 下棋；下国际象棋；着棋"]},{"name":"drink","trans":["n. 酒，饮料；喝酒,vt. 喝，饮；吸收；举杯庆贺,vi. 喝酒；饮水；干杯"]},{"name":"soya milk","trans":["n. 豆浆, 豆奶；大豆奶；豆乳"]},{"name":"clock","trans":["n. 时钟；计时器,vt. 记录；记时,vi. 打卡；记录时间"]},{"name":"hungry","trans":["adj. 饥饿的；渴望的；荒年的；不毛的"]},{"name":"Me too.","trans":["找不到解释"]},{"name":"draw","trans":["n. 平局；抽签,vi. 拉；拖,vt. 画；拉；吸引"]},{"name":"jump","trans":["n. 跳跃；暴涨；惊跳,vt. 跳跃；使跳跃；跳过；突升,vi. 跳跃；暴涨；猛增"]},{"name":"sing","trans":["n. 演唱；鸣声；呼啸声,vt. 唱；用诗赞颂；唱着使,vi. 唱歌；歌颂；鸣叫；呼号"]},{"name":"dance","trans":["n. 舞蹈；舞会；舞曲,adj. 舞蹈的；用于跳舞的,vt. 跳舞；使跳跃,vi. 跳舞；跳跃；飘扬"]},{"name":"want","trans":["n. 需要；缺乏；贫困；必需品,vt. 需要；希望；应该；缺少,vi. 需要；缺少"]},{"name":"some","trans":["adj. 一些；某个；大约；相当多的,pron. 一些；若干；其中的一部分；（数量不确切时用）有些人,adv. 非常；相当；<美>稍微"]},{"name":"juice","trans":["n. （水果）汁，液；果汁"]},{"name":"ice","trans":["n. 冰；冰淇淋；矜持；（俚）钻石,adj. 冰的,vt. 冰镇；结冰,vi. 结冰"]},{"name":"also","trans":["conj. 并且；另外,adv. 也；而且；同样"]},{"name":"food","trans":["n. 食物；养料"]},{"name":"fast food","trans":["n. 快餐；速食, 快餐食品；快餐店；速食店"]},{"name":"make","trans":["vt. 使得；进行；布置，准备，整理；制造；认为；获得；形成；安排；引起；构成,vi. 开始；前进；增大；被制造,n. 制造；构造；性情"]},{"name":"tomato","trans":["n. 番茄，西红柿"]},{"name":"egg","trans":["n. 蛋；卵子；家伙；鸡蛋,vt. 煽动；怂恿"]},{"name":"potato","trans":["n.  土豆， 马铃薯"]},{"name":"How much ...?","trans":["找不到解释"]},{"name":"flower","trans":["n. 花；精华；开花植物,vt. 使开花；用花装饰,vi. 成熟，发育；开花；繁荣；旺盛"]},{"name":"dumpling","trans":["n. 饺子，汤团；面团布丁"]},{"name":"help","trans":["n. 帮助；补救办法；帮忙者；有益的东西,vt. 帮助；促进；治疗；补救,vi. 帮助；有用；招待"]},{"name":"buy","trans":["n. 购买，买卖；所购的物品,vi. 买，采购,vt. 购买；获得；贿赂"]},{"name":"run","trans":["n. 奔跑；赛跑；趋向；奔跑的路程,vt. 管理，经营；运行；参赛,vi. 经营；奔跑；运转"]},{"name":"fast","trans":["n. 斋戒；绝食,adj. 快速的，迅速的；紧的，稳固的,adv. 迅速地；紧紧地；彻底地,vi. 禁食，斋戒"]},{"name":"sky","trans":["n. 天空；顶点,vt. 把…投向空中；把…挂得过高,vi. 踢或击高空球；把桨叶翘得过高；飞涨"]},{"name":"high","trans":["n. 高水平；天空；由麻醉品引起的快感；高压地带,adj. 高的；高级的；崇高的；高音调的,adv. 高；奢侈地"]},{"name":"winner","trans":["n. 胜利者"]},{"name":"far","trans":["n. 远方,adj. 远的；久远的,adv. 很；遥远地；久远地；到很远的距离；到很深的程度"]},{"name":"afraid","trans":["adj. 害怕的；恐怕；担心的"]},{"name":"strong","trans":["adj. 坚强的；强壮的；牢固的；擅长的,adv. 强劲地；猛烈地"]},{"name":"star","trans":["n. 星，恒星；明星；星形物,adj. 明星的，主角的；星形的,vt. 用星号标于；由…主演，由…担任主角,vi. 担任主角"]},{"name":"sweets","trans":["n. 糖果；甜食（sweet的复数）"]},{"name":"soup","trans":["n. 汤，羹；马力,vt. 加速；增加马力"]},{"name":"sorry","trans":["adj. 遗憾的；对不起的，抱歉的,int. 对不起，抱歉（表示委婉的拒绝等）"]},{"name":"bread","trans":["n. 面包；生计,vt. 在…上洒面包屑"]},{"name":"dark","trans":["n. 黑暗；夜；黄昏；模糊,adj. 黑暗的，深色的；模糊的；无知的；忧郁的"]},{"name":"well","trans":["n. 井；源泉,adj. 良好的；健康的；适宜的,adv. 很好地；充分地；满意地；适当地,v. 涌出"]},{"name":"turn on","trans":["na. 转向；对…进行突击, 打开；接通；开启"]},{"name":"light","trans":["n. 光；光线；灯；打火机；领悟；浅色；天窗,adj. 轻的；浅色的；明亮的；轻松的；容易的；清淡的,vi. 点着；变亮；着火,vt. 照亮；点燃；着火,adv. 轻地；清楚地；轻便地"]},{"name":"Halloween","trans":["n. 万圣节前夕（指十月三十一日夜晚）"]},{"name":"trick or treat","trans":["int. 不给糖就捣蛋,n. 不给糖就捣蛋, 不给糖就捣乱；不给糖便会捣蛋；不请吃就捣蛋"]},{"name":"give","trans":["n. 弹性；弯曲；伸展性,vi. 捐赠；面向；有弹性；气候转暖,vt. 给；产生；让步；举办；授予"]},{"name":"come in","trans":["na. 进入；当选；上台；(党派)组阁, 进来；请进；流行起来"]},{"name":"of course","trans":["na. 当然, 自然；当然可以；当然了"]},{"name":"there is","trans":["na.  有, 那儿有；现在有；存在"]},{"name":"horse","trans":["n. 马；骑兵；脚架；海洛因,vt. 使骑马；系马于；捉弄,vi. 骑马；作弄人"]},{"name":"there are","trans":["有…,存在着…"]},{"name":"have a look","trans":["v. 看一看, 看一下；瞧一瞧；看看"]},{"name":"sheep","trans":["n. 羊，绵羊；胆小鬼"]},{"name":"vegetable","trans":["n. 蔬菜；植物；植物人,adj. 蔬菜的；植物的"]},{"name":"climb","trans":["n. 爬；攀登,vi. 爬；攀登；上升,vt. 爬；攀登；上升"]},{"name":"face","trans":["n. 脸；表面；面子；面容；外观；威信,vi. 向；朝,vt. 面对；面向；承认；抹盖"]},{"name":"fruit","trans":["n. 水果；产物,vt. 使……结果实,vi. 结果实"]},{"name":"chicken","trans":["n. 鸡肉；小鸡；胆小鬼，懦夫,adj. 鸡肉的；胆怯的；幼小的"]},{"name":"bear","trans":["n. 熊,vt. 结果实，开花（正式）,vt. 忍受；承受；具有；支撑"]},{"name":"pig","trans":["n. 猪；猪肉,vi. 生小猪；像猪一样过活,n. 警察（俚语，带有攻击性）"]},{"name":"visit","trans":["n. 访问；参观；逗留,vt. 访问；参观；视察,vi. 访问；暂住；闲谈"]},{"name":"tomorrow","trans":["n. 明天；未来,adv. 明天；未来地（等于to-morrow）"]},{"name":"plane","trans":["n. 飞机；平面；程度，水平,adj. 平的；平面的,vt. 刨平；用刨子刨；掠过水面,vi. 刨；乘飞机旅行；翱翔"]},{"name":"get up","trans":["na. 起床；起身；站起来；叫…起床, 起立；打扮；安排"]},{"name":"o'clock","trans":["abbr. …点钟（等于of the clock）"]},{"name":"from","trans":["prep. 来自，从；由于；今后"]},{"name":"sea","trans":["n. 海；海洋；许多；大量"]},{"name":"swimsuit","trans":["n. 游泳衣（女式）"]},{"name":"sock","trans":["vt. 重击；给……穿袜,n. 短袜；一击,adv. 正着地；不偏不倚地,adj. 非常成功的"]},{"name":"fish","trans":["n. 鱼，鱼类,vt. 钓鱼，捕鱼；搜寻,vi. 捕鱼，钓鱼；用钩捞取"]},{"name":"hooray","trans":["n. 万岁,vt. 呼万岁,int. 万岁,vi. 呼万岁"]},{"name":"sports day","trans":["n. （学校的）运动会, 运动日；体育日；开运动会的日子"]},{"name":"win","trans":["n. 赢；胜利,vt. 赢得；在…中获胜；劝诱,vi. 赢；获胜；成功"]},{"name":"month","trans":["n. 月，一个月的时间"]},{"name":"hundred","trans":["num. 百；百个,n. 一百；许多,adj. 一百的；许多的"]},{"name":"metre","trans":["n. 米；公尺；韵律"]},{"name":"every","trans":["adj. 每一的，每个的；每隔…的"]},{"name":"day","trans":["n. 一天；时期；白昼,adj. 日间的；逐日的,adv. 每天；经常在白天地"]},{"name":"luck","trans":["n. 运气；幸运；带来好运的东西,vi. 靠运气，走运；凑巧碰上"]},{"name":"good luck","trans":["na. 幸运, 祝你好运；祝好运；好运气"]},{"name":"come on","trans":["na. (演员)出台；进行(很好)；(暴风雨等)起；(病,苦痛等)加深, 来吧；加油；快点"]},{"name":"high jump","trans":["n. 跳高, 高跳；跳远；高台跳高"]},{"name":"long jump","trans":["n. 跳远, 长跳；长跳转；长转移"]},{"name":"How about ...?","trans":["找不到解释"]},{"name":"subject","trans":["n. 主题；科目； 主语；国民,adj. 服从的；易患…的；受制于…的,vt. 使…隶属；使屈从于…"]},{"name":"family","trans":["n. 家庭；亲属；家族；子女；科；语族；族,adj. 家庭的；家族的；适合于全家的"]},{"name":"dinner","trans":["n. 晚餐，晚宴；宴会；正餐"]},{"name":"year","trans":["n. 年；年度；历年；年纪；一年的期间；某年级的学生"]},{"name":"New Year","trans":["n. 新年, 元旦；新年元旦；公历新年"]},{"name":"Chinese","trans":["n. 中文，汉语；中国人,adj. 中国的，中国人的；中国话的"]},{"name":"festival","trans":["n. 节日；庆祝，纪念活动；欢乐,adj. 节日的，喜庆的；快乐的"]},{"name":"the Spring Festival","trans":["找不到解释"]},{"name":"I see.","trans":["找不到解释"]},{"name":"peanut","trans":["n. 花生"]},{"name":"merry","trans":["adj. 愉快的；微醉的；嬉戏作乐的,n. 甜樱桃"]},{"name":"Christmas","trans":["n. 圣诞节；圣诞节期间"]},{"name":"Merry Christmas!","trans":["na. 圣诞快乐, 圣诞节快乐；祝你圣诞快乐；耶诞快乐"]}]