[{"name":"senior","trans":["n. 上司；较年长者；毕业班学生,adj. 高级的；年长的；地位较高的；年资较深的，资格较老的"]},{"name":"senior high","trans":["na. 高级中学(10--12年级), 高中；高中部；高中以上"]},{"name":"curious","trans":["adj. 好奇的，有求知欲的；古怪的；爱挑剔的"]},{"name":"impression","trans":["n. 印象；效果，影响；压痕，印记；感想；曝光（衡量广告被显示的次数。打开一个带有该广告的网页，则该广告的impression 次数增加一次）"]},{"name":"campus","trans":["n. （大学）校园；大学，大学生活；校园内的草地"]},{"name":"tradition","trans":["n. 惯例，传统；传说"]},{"name":"facility","trans":["n. 设施；设备；容易；灵巧"]},{"name":"impressive","trans":["adj. 感人的；令人钦佩的；给人以深刻印象的"]},{"name":"moment","trans":["n. 片刻，瞬间，时刻；重要，契机"]},{"name":"author","trans":["n. 作者；作家；创始人,vt. 创作出版"]},{"name":"eagerness","trans":["n. 渴望；热心"]},{"name":"explore","trans":["vi. 探索；探测；探险,vt. 探索；探测；探险"]},{"name":"one by one","trans":["na. 一个一个；一个一个地, 一个接一个；一个接一个地；一个接着一个"]},{"name":"engine","trans":["n. 引擎，发动机；机车，火车头；工具"]},{"name":"insect","trans":["n. 昆虫；卑鄙的人"]},{"name":"collection","trans":["n. 采集，聚集； 征收；收藏品；募捐"]},{"name":"organise","trans":["vi. 组织起来；组织工会,vt. 组织（等于organize）；有机化；给予生机"]},{"name":"nudge","trans":["n. 推动；用肘轻推；没完没了抱怨的人,vt. 推进；用肘轻推；向…不停地唠叨,vi. 轻推；推进；唠叨"]},{"name":"butterfly","trans":["n. 蝴蝶；蝶泳；举止轻浮的人；追求享乐的人"]},{"name":"butterflies in one's stomach","trans":["因害怕(或焦虑)而引起的紧张"]},{"name":"breathe","trans":["vi. 呼吸；低语；松口气；（风）轻拂,vt. 呼吸；使喘息；流露；低声说"]},{"name":"panic","trans":["n. 恐慌，惊慌；大恐慌,adj. 恐慌的；没有理由的,vt. 使恐慌,vi. 十分惊慌"]},{"name":"in panic","trans":[" 惊慌失措地；惊慌地；在恐慌中"]},{"name":"challenge","trans":["n. 挑战；怀疑,vt. 向…挑战；对…质疑"]},{"name":"pressure","trans":["n. 压力；压迫， 压强,vt. 迫使；密封；使……增压"]},{"name":"calm","trans":["n. 风平浪静,adj. 静的，平静的；沉着的,vt. 使平静；使镇定,vi. 平静下来；镇定下来"]},{"name":"description","trans":["n. 描述，描写；类型；说明书"]},{"name":"confident","trans":["adj. 自信的；确信的"]},{"name":"poster","trans":["n. 海报，广告；招贴"]},{"name":"badminton","trans":["n. 羽毛球"]},{"name":"drama","trans":["n. 戏剧，戏剧艺术；剧本；戏剧性事件"]},{"name":"band","trans":["n. 带，环； 波段；(演奏流行音乐的) 乐队,n. n.乐队；队；一群,vi. 用带绑扎；给...镶边"]},{"name":"debate","trans":["n. 辩论；辩论会,vt. 辩论，争论，讨论,vi. 辩论，争论，讨论"]},{"name":"gym","trans":["n. 健身房；体育；体育馆"]},{"name":"piano","trans":["n. 钢琴"]},{"name":"stage","trans":["n. 阶段；舞台；戏剧；驿站,vt. 举行；上演；筹划,vi. 举行；适于上演；乘驿车旅行"]},{"name":"photography","trans":["n. 摄影；摄影术"]},{"name":"inner","trans":["n. 内部,adj. 内部的；内心的；精神的"]},{"name":"pm","trans":["找不到解释"]},{"name":"argue","trans":["vi. 争论，辩论；提出理由,vt. 辩论，争论；证明；说服"]},{"name":"topic","trans":["n. 主题（等于theme）；题目；一般规则；总论"]},{"name":"sharp","trans":["n. 尖头；骗子；内行,adj. 急剧的；锋利的；强烈的；敏捷的；刺耳的,vt. 磨快；把音调升高,adv. 急剧地；锐利地；突然地,vi. 打扮；升音演奏"]},{"name":"dinosaur","trans":["n. 恐龙；过时、落伍的人或事物"]},{"name":"dolphin","trans":["n. 海豚"]},{"name":"intelligent","trans":["adj. 智能的；聪明的；理解力强的"]},{"name":"investigate","trans":["v. 调查；研究"]},{"name":"various","trans":["adj. 各种各样的；多方面的"]},{"name":"volunteer","trans":["n. 志愿者；志愿兵,adj. 志愿的,vt. 自愿,vi. 自愿"]},{"name":"gain","trans":["n. 增加；利润；收获,vi. 增加；获利,vt. 获得；增加；赚到"]},{"name":"apply","trans":["vi. 申请；涂，敷；适用；请求,vt. 申请；涂，敷；应用"]},{"name":"schedule","trans":["n. 时间表；计划表；一览表,vt. 安排，计划；编制目录；将……列入计划表"]},{"name":"award","trans":["n. 奖品；判决,vt. 授予；判定"]},{"name":"opportunity","trans":["n. 时机，机会"]},{"name":"hint","trans":["n. 暗示；线索,vt. 暗示；示意,vi. 示意"]},{"name":"subscribe","trans":["vt. 签署；赞成；捐助,vi. 订阅；捐款；认购；赞成；签署"]},{"name":"view","trans":["n. 观察；视野；意见；风景,vt. 观察；考虑；查看"]},{"name":"former","trans":["n. 模型，样板；起形成作用的人,adj. 从前的，前者的；前任的"]},{"name":"graduate","trans":["n. 研究生；毕业生,adj. 毕业的；研究生的,vt. 授予…学位；分等级；标上刻度,vi. 毕业；渐变"]},{"name":"orientation","trans":["n. 方向；定向；适应；情况介绍；向东方"]},{"name":"Orientation Day","trans":["找不到解释"]},{"name":"frightened","trans":["v. 害怕；使吃惊；吓走（frighten的过去分词）,adj. 害怕的；受惊的；受恐吓的"]},{"name":"sight","trans":["n. 视力；景象；眼界；见解,adj. 见票即付的；即席的,vt. 看见；瞄准,vi. 瞄准；观看"]},{"name":"figure","trans":["n. 数字；人物；图形；价格；（人的）体形；画像,vt. 计算；认为；描绘；象征,vi. 计算；出现；扮演角色"]},{"name":"go all out","trans":["abbr. (=go all-out)全力以赴, 鼓足干劲；不遗余力；不惜一切代价"]},{"name":"select","trans":["n. 被挑选者；精萃,adj. 精选的；挑选出来的；极好的,vt. 挑选；选拔,vi. 挑选"]},{"name":"particular","trans":["n. 详细说明；个别项目,adj. 特别的；详细的；独有的；挑剔的"]},{"name":"in particular","trans":["na. 特别；一一, 尤其；特别地；特别是"]},{"name":"rainbow","trans":["n. 彩虹；五彩缤纷的排列；幻想,adj. 五彩缤纷的；彩虹状的,vt. 使呈彩虹状；如彩虹般装饰,vi. 呈彩虹状"]},{"name":"neat","trans":["adj. 灵巧的；整洁的；优雅的；齐整的；未搀水的；平滑的"]},{"name":"specific","trans":["n. 特性；细节；特效药,adj. 特殊的，特定的；明确的；详细的； 具有特效的"]},{"name":"refer","trans":["vt. 涉及；委托；归诸于；使…求助于,vi. 参考；涉及；提到；查阅"]},{"name":"refer to","trans":["v. 查阅；提到, 参考；涉及；谈到"]},{"name":"journal","trans":["n. 日报，杂志；日记；分类账"]},{"name":"junior","trans":["adj. 年少的；后进的；下级的,n. 年少者，晚辈；地位较低者；大学三年级学生"]},{"name":"struggle","trans":["n. 努力，奋斗；竞争,vt. 使劲移动；尽力使得,vi. 奋斗，努力；挣扎"]},{"name":"memorise","trans":["vt. （英）记忆；存储（等于memorize）"]},{"name":"skateboarding","trans":["n. 滑板运动"]},{"name":"forward","trans":["n. 前锋,adj. 向前的；早的；迅速的,adv. 向前地；向将来,vt. 促进；转寄；运送"]},{"name":"look forward to","trans":["na. 盼望, 期待；期望；期盼"]},{"name":"committee","trans":["n. 委员会"]},{"name":"improve","trans":["vt. 改善，增进；提高…的价值,vi. 增加；变得更好"]},{"name":"rate","trans":["n. 比率，率；速度；价格；等级,vt. 认为；估价；责骂,vi. 责骂；被评价"]},{"name":"performance","trans":["n. 性能；绩效；表演；执行；表现"]},{"name":"exchange","trans":["n. 交换；交流；交易所；兑换,vt. 交换；交易；兑换,vi. 交换；交易；兑换"]},{"name":"title","trans":["n. 冠军；标题；头衔；权利；字幕,adj. 冠军的；标题的；头衔的,vt. 加标题于；赋予头衔；把…称为"]},{"name":"ham","trans":["adj. 过火的；做作的,vi. 表演过火,vt. 演得过火,n. 火腿；业余无线电爱好者；蹩脚演员"]},{"name":"eggplant","trans":["n. 茄子,adj. 深紫色的"]},{"name":"pine","trans":["n.  松树；凤梨，菠萝,adj. 松木的；似松的,vt. 为…悲哀；哀悼,vi. 渴望，痛苦；憔悴"]},{"name":"pineapple","trans":["n.  菠萝； 凤梨,adj. 凤梨科的"]},{"name":"sculpt","trans":["n. 雕刻品,vt. 造型；雕刻,vi. 造型；雕刻"]},{"name":"sculpture","trans":["n. 雕塑；雕刻；刻蚀,vt. 雕塑；雕刻；刻蚀,vi. 从事雕刻"]},{"name":"seasick","trans":["adj. 晕船的,晕船"]},{"name":"airsick","trans":["adj. 晕机的；患航空病的"]},{"name":"carsick","trans":["adj. 晕车的"]},{"name":"homesick","trans":["adj. 想家的；思乡病的"]},{"name":"opposing","trans":["adj. 反对的；相对的；对面的,v. 反对（oppose的ing形式）"]},{"name":"behavior","trans":["n. 行为，举止；态度；反应"]},{"name":"confusing","trans":["v. 使迷惑；使混乱不清；使困窘（confuse的ing形式）,adj. 混乱的；混淆的；令人困惑的"]},{"name":"capitalized","trans":["大写的"]},{"name":"unique","trans":["n. 独一无二的人或物,adj. 独特的，稀罕的； 唯一的，独一无二的"]},{"name":"burn up","trans":["na. 烧完；旺起来；使恼怒；发怒, 烧起来；烧尽；烧光"]},{"name":"burn down","trans":["na. 把…烧成平地；(蜡烛等)逐渐烧完；火力减弱, 烧毁；烧光；烧为平地"]},{"name":"alarm","trans":["n. 闹钟；警报，警告器；惊慌,vt. 警告；使惊恐"]},{"name":"reflect","trans":["vt. 反映；反射，照出；表达；显示;反省,vi. 反射，映现；深思"]},{"name":"creativity","trans":["n. 创造力；创造性"]},{"name":"visible","trans":["n. 可见物；进出口贸易中的有形项目,adj. 明显的；看得见的；现有的；可得到的"]},{"name":"wind up","trans":["结束；使紧张；卷起；（非正式）忽悠某人（wind sb up）；上紧(钟、表等的)发条"]},{"name":"creative","trans":["adj. 创造性的"]},{"name":"type","trans":["n. 类型，品种；模范；样式,vt. 打字；测定（血等）类型,vi. 打字"]},{"name":"come across","trans":["na. 尽(义务)；发现；碰见；(穿过…)来到, 遇见；偶然遇见；碰到"]},{"name":"unfamiliar","trans":["adj. 不熟悉的；不常见的；没有经验的"]},{"name":"contact","trans":["n. 接触，联系,vt. 使接触，联系,vi. 使接触，联系"]},{"name":"organization","trans":["n. 组织；机构；体制；团体"]},{"name":"likely","trans":["adj. 很可能的；合适的；有希望的,adv. 很可能；或许"]},{"name":"subway","trans":["n. 地铁；地道,vi. 乘地铁"]},{"name":"highway","trans":["n. 公路，大路；捷径"]},{"name":"motorway","trans":["n. 高速公路，汽车高速公路"]},{"name":"gas","trans":["n. 气体； 瓦斯；汽油；毒气,vt. 加油；毒（死）,vi. 加油；放出气体；空谈"]},{"name":"petrol","trans":["n. （英）汽油"]},{"name":"apartment","trans":["n. 公寓；房间"]},{"name":"flat","trans":["n. 平地；公寓；平面,adj. 平的；单调的；不景气的；干脆的；平坦的；扁平的；浅的,vi. 逐渐变平；以降调唱（或奏）,vt. 使变平；使（音调）下降，尤指降半音,adv. （尤指贴着另一表面）平直地；断然地；水平地；直接地，完全地"]},{"name":"elevator","trans":["n. 电梯；升降机；升降舵；起卸机"]},{"name":"context","trans":["n. 环境；上下文；来龙去脉"]},{"name":"addition","trans":["n. 添加； 加法；增加物"]},{"name":"forum","trans":["n. 论坛，讨论会；法庭；公开讨论的广场"]},{"name":"resource","trans":["n. 资源，财力；办法；智谋"]},{"name":"misadventure","trans":["n. 灾难；不幸遭遇"]},{"name":"remind","trans":["vt. 提醒；使想起"]},{"name":"rather","trans":["adv. 宁可，宁愿；相当,int. 当然啦（回答问题时用）"]},{"name":"comment","trans":["n. 评论；意见；批评,vi. 发表评论；发表意见,vt. 为…作评语"]},{"name":"frog","trans":["n. 青蛙； 辙叉；饰扣,vi. 捕蛙"]},{"name":"throat","trans":["n. 喉咙；嗓子，嗓音；窄路,vt. 开沟于；用喉音说"]},{"name":"have a frog in one's throat","trans":["（非正式）（因嗓音嘶哑）失声，很难发声"]},{"name":"downtown","trans":["n. 市中心区；三分线以外,adj. 市中心的,adv. 往闹市区；在市区"]},{"name":"boot","trans":["n. 靴子；踢；汽车行李箱,vt. 引导；踢；解雇；使穿靴"]},{"name":"entrance","trans":["n. 入口；进入,vt. 使出神，使入迷"]},{"name":"section","trans":["n. 截面；部分；部门；地区；章节,vt. 把…分段；将…切片；对…进行划分,vi. 被切割成片；被分成部分"]},{"name":"exit","trans":["n. 出口，通道；退场,vi. 退出；离去"]},{"name":"actually","trans":["adv. 实际上；事实上"]},{"name":"downstairs","trans":["n. 楼下,adj. 楼下的,adv. 在楼下"]},{"name":"wicked","trans":["adj. 邪恶的；恶劣的；不道德的；顽皮的"]},{"name":"odd","trans":["adj. 奇数的；古怪的；剩余的；临时的；零散的,n. 奇数；怪人；奇特的事物"]},{"name":"negative","trans":["adj.  负的；消极的；否定的；阴性的,n. 否定；负数； 底片,vt. 否定；拒绝"]},{"name":"error","trans":["n. 误差；错误；过失"]},{"name":"intend","trans":["vi. 有打算,vt. 打算；想要；意指"]},{"name":"informal","trans":["adj. 非正式的；不拘礼节的；随便的；通俗的；日常使用的"]},{"name":"recognise","trans":["vt. 认出；承认，认可；识别"]},{"name":"base","trans":["n. 基础；底部；垒,adj. 卑鄙的；低劣的,vt. 以…作基础"]},{"name":"aware","trans":["adj. 意识到的；知道的；有…方面知识的；懂世故的"]},{"name":"be aware of","trans":["na. 知道, 意识到；觉察；了解"]},{"name":"character","trans":["n. 性格，品质；特性；角色； 字符,vt. 印，刻；使具有特征"]},{"name":"approach","trans":["n. 方法；途径；接近,vt. 接近；着手处理,vi. 靠近"]},{"name":"chat","trans":["n. 聊天；闲谈,vt. 与…搭讪；与…攀谈,vi. 聊天；闲谈"]},{"name":"focus","trans":["n. 焦点；中心；清晰；焦距,vt. 使集中；使聚焦,vi. 集中；聚焦；调节焦距"]},{"name":"career","trans":["n. 生涯；职业；事业；速度，全速,adj. 作为毕生职业的,vi. 全速前进，猛冲"]},{"name":"lawyer","trans":["n. 律师；法学家"]},{"name":"assume","trans":["vt. 僭取；篡夺；夺取；擅用；侵占,vi. 假定；设想；承担；采取"]},{"name":"respect","trans":["n. 尊敬，尊重；方面；敬意,vt. 尊敬，尊重；遵守"]},{"name":"studio","trans":["n. 工作室； 演播室；画室；电影制片厂"]},{"name":"court","trans":["n. 法院；球场；朝廷；奉承,vt. 招致（失败、危险等）；向…献殷勤；设法获得,vi. 求爱"]},{"name":"ignore","trans":["vt. 驳回诉讼；忽视；不理睬"]},{"name":"professional","trans":["n. 专业人员；职业运动员,adj. 专业的；职业的；职业性的"]},{"name":"suit","trans":["n. 诉讼；恳求；套装，西装；一套外衣,vt. 适合；使适应,vi. 合适；相称"]},{"name":"talent","trans":["n. 才能；天才；天资"]},{"name":"option","trans":["n.  选项；选择权；买卖的特权"]},{"name":"sigh","trans":["n. 叹息，叹气,vt. 叹息，叹气,vi. 叹息，叹气"]},{"name":"curtain","trans":["n. 幕；窗帘,vt. 遮蔽；装上门帘"]},{"name":"generation","trans":["n. 一代；产生；一代人；生殖"]},{"name":"gap","trans":["n. 间隙；缺口；差距；分歧,vt. 使形成缺口,vi. 裂开"]},{"name":"currently","trans":["adv. 当前；一般地"]},{"name":"regularly","trans":["adv. 定期地；有规律地；整齐地；匀称地"]},{"name":"responsible","trans":["adj. 负责的，可靠的；有责任的"]},{"name":"memory","trans":["n. 记忆，记忆力；内存， 存储器；回忆"]},{"name":"nowadays","trans":["adv. 现今；时下,n. 当今"]},{"name":"jaw","trans":["n. 颌；下巴；狭窄入口；唠叨,vt. 教训；对…唠叨,vi. 教训；唠叨"]},{"name":"beard","trans":["n. 胡须；颌毛,vt. 公然反对；抓…的胡须,vi. 充当掩护；充当男随员"]},{"name":"skin","trans":["n. 皮肤；外皮,vt. 剥皮,vi. 愈合；长皮"]},{"name":"jogging","trans":["n. 慢跑,v. 慢跑（jog的ing形式）；轻推；唤起"]},{"name":"slim","trans":["adj. 苗条的；修长的；微小的；差的,vt. 使…体重减轻；使…苗条,vi. 减轻体重；变细"]},{"name":"cheek","trans":["n. 面颊，脸颊；臀部,vt. 无礼地向…讲话，对…大胆无礼"]},{"name":"nation","trans":["n. 国家；民族；国民"]},{"name":"aim","trans":["n. 目的；目标；对准,vt. 目的在于；引导；把…对准,vi. 打算；对准目标；瞄准"]},{"name":"issue","trans":["n. 问题；流出；期号；发行物,vt. 发行，发布；发给；放出，排出,vi. 发行；流出；造成…结果；传下"]},{"name":"theme","trans":["n. 主题；主旋律；题目,adj. 以奇想主题布置的"]},{"name":"observe","trans":["vt. 庆祝,vt. 观察；遵守；说；注意到；评论,vi. 观察；说；注意到；评论"]},{"name":"range","trans":["n. 范围；幅度；排；山脉,vt. 漫游；放牧；使并列；归类于；来回走动,vi. （在...内）变动；平行，列为一行；延伸；漫游；射程达到"]},{"name":"event","trans":["n. 事件，大事；项目；结果"]},{"name":"apologise","trans":["vi. 道歉（等于apologize）"]},{"name":"stress","trans":["n. 压力；强调；紧张；重要性；重读,vt. 强调；使紧张；加压力于；用重音读"]},{"name":"impact","trans":["vi. 影响；撞击；冲突；压紧（on，upon，with）,n. 影响；效果；碰撞；冲击力,vt. 挤入，压紧；撞击；对…产生影响"]},{"name":"strength","trans":["n. 力量；力气；兵力；长处"]},{"name":"admire","trans":["vt. 钦佩；赞美,vi. 钦佩；称赞"]},{"name":"judge","trans":["vt. 判断；审判,n. 法官；裁判员,vi. 审判；判决"]},{"name":"settle","trans":["n. 有背长椅,vi. 解决；定居；沉淀；下陷,vt. 解决；安排；使…定居"]},{"name":"settle for","trans":["na. 满足于, 勉强接受；将就；勉强认可"]},{"name":"feature","trans":["n. 特色，特征；容貌；特写或专题节目,vt. 特写；以…为特色；由…主演,vi. 起重要作用"]},{"name":"typically","trans":["adv. 代表性地；作为特色地"]},{"name":"individual","trans":["n. 个人，个体,adj. 个人的；个别的；独特的"]},{"name":"style","trans":["n. 风格；时尚；类型；字体,vt. 设计；称呼；使合潮流,vi. 设计式样；用刻刀作装饰画"]},{"name":"extra","trans":["n. 临时演员；号外；额外的事物；上等产品,adj. 额外的，另外收费的；特大的,adv. 特别地，非常；另外"]},{"name":"detail","trans":["n. 细节，详情,vt. 详述；选派,vi. 画详图"]},{"name":"contain","trans":["vi. 含有；自制,vt. 包含；控制；容纳；牵制（敌军）"]},{"name":"summary","trans":["n. 概要，摘要，总结,adj. 简易的；扼要的"]},{"name":"powerful","trans":["adj. 强大的；强有力的,adv. 很；非常"]},{"name":"triathlon","trans":["n. 三项全能运动"]},{"name":"series","trans":["n. 系列，连续； 串联；级数；丛书"]},{"name":"in the lead","trans":[" 处于领先地位；带头；占主导地位的"]},{"name":"onto","trans":["prep. 在…之上；对…了解；映射到…上,adj. 映射的；自身的；映成的"]},{"name":"track","trans":["n. 轨道；足迹，踪迹；小道,vt. 追踪；通过；循路而行；用纤拉,vi. 追踪；走；留下足迹"]},{"name":"media","trans":["n. 媒体；媒质（medium的复数）；血管中层；浊塞音；中脉"]},{"name":"obviously","trans":["adv. 明显地,显然地"]},{"name":"despite","trans":["prep. 尽管，不管,n. 轻视；憎恨；侮辱"]},{"name":"throughout","trans":["prep. 贯穿，遍及,adv. 自始至终，到处；全部"]},{"name":"entire","trans":["adj. 全部的，整个的；全体的"]},{"name":"enormously","trans":["adv. 巨大地，庞大地；非常地，在极大程度上"]},{"name":"positive","trans":["n. 正数； 正片,adj. 积极的； 正的， 阳性的；确定的，肯定的；实际的，真实的；绝对的"]},{"name":"million","trans":["n. 百万；无数,adj. 百万的；无数的,num. 百万"]},{"name":"disqualify","trans":["vt. 取消…的资格"]},{"name":"athlete","trans":["n. 运动员，体育家；身强力壮的人"]},{"name":"medal","trans":["n. 勋章，奖章；纪念章"]},{"name":"somehow","trans":["adv. 以某种方法；莫名其妙地"]},{"name":"indeed","trans":["adv. 的确；实在；真正地；甚至,int. 真的（表示惊讶、怀疑、讽刺等）"]},{"name":"forever","trans":["adv. 永远；不断地；常常"]},{"name":"familiar","trans":["n. 常客；密友,adj. 熟悉的；常见的；亲近的"]},{"name":"adventure","trans":["n. 冒险；冒险精神；投机活动,vt. 冒险；大胆说出,vi. 冒险"]},{"name":"prefer","trans":["vt. 更喜欢；宁愿；提出；提升,vi. 喜欢；愿意"]},{"name":"lose track of","trans":["na. 忘记, 失去线索；失去联系；失去消息"]},{"name":"deliver","trans":["n. 投球,vt. 交付；发表；递送；释放；给予（打击）；给…接生,vi. 实现；传送；履行；投递"]},{"name":"thanks to","trans":["v. 感谢；幸亏；多亏, 由于；多亏了；归功于"]},{"name":"advance","trans":["n. 发展；前进；增长；预付款,adj. 预先的；先行的,vt. 提出；预付；使……前进；将……提前,vi. 前进；进展；上涨"]},{"name":"significantly","trans":["adv. 显著地；相当数量地"]},{"name":"social media","trans":[" 社会化媒体（具体形式有博客、维基、播客、论坛、社交网络、内容社区等）"]},{"name":"maintain","trans":["vt. 维持；继续；维修；主张；供养"]},{"name":"wi-fi","trans":["abbr. 无线保真技术（wireless fidelity）；无线上网技术"]},{"name":"click","trans":["n. 单击；滴答声,vi. 作咔哒声,vt. 点击；使发咔哒声"]},{"name":"digital","trans":["n. 数字；键,adj. 数字的；手指的"]},{"name":"enable","trans":["vt. 使能够，使成为可能；授予权利或方法"]},{"name":"unusual","trans":["adj. 不寻常的；与众不同的；不平常的"]},{"name":"site","trans":["n. 地点；位置；场所,vt. 设置；为…选址"]},{"name":"tend","trans":["vt. 照料，照管,vi. 趋向，倾向；照料，照顾"]},{"name":"update","trans":["n. 更新；现代化,vt. 更新；校正，修正；使现代化"]},{"name":"saying","trans":["n. 话；谚语；言论,v. 说（say的ing形式）"]},{"name":"criminal","trans":["n. 罪犯,adj. 刑事的；犯罪的；罪恶的"]},{"name":"bathwater","trans":["n. 浴缸里的水；洗涤用水"]},{"name":"throw the baby out with the bathwater","trans":["不分精华糟粕全盘否定"]},{"name":"acquire","trans":["vt. 获得；取得；学到；捕获"]},{"name":"goods","trans":["n. 商品；动产；合意的人；真本领"]},{"name":"prove","trans":["vi. 证明是,vt. 证明；检验；显示"]},{"name":"illustrate","trans":["vi. 举例,vt. 阐明，举例说明；图解"]},{"name":"diagram","trans":["n. 图表；图解,vt. 用图解法表示"]},{"name":"inspiring","trans":["v. 鼓舞；激发；使感悟（inspire的ing形式）,adj. 鼓舞人心的；灌输的；启发灵感的"]},{"name":"teenager","trans":["n. 十几岁的青少年；十三岁到十九岁的少年"]},{"name":"pour","trans":["n. 倾泻；流出；骤雨,vt. 灌，注；倒；倾泻；倾吐,vi. 倾泻；涌流；斟茶"]},{"name":"pot","trans":["n. 壶；盆；罐,vt. 把…装罐；射击；节略,vi. 随手射击"]},{"name":"gram","trans":["n. 克；鹰嘴豆（用作饲料）"]},{"name":"pack","trans":["n. 包装；一群；背包；包裹；一副,vt. 包装；压紧；捆扎；挑选；塞满,vi. 挤；包装货物；被包装；群集"]},{"name":"comfort","trans":["n. 安慰；舒适；安慰者,vt. 安慰；使（痛苦等）缓和"]},{"name":"patience","trans":["n. 耐性，耐心；忍耐，容忍"]},{"name":"passion","trans":["n. 激情；热情；酷爱；盛怒"]},{"name":"generosity","trans":["n. 慷慨，大方；宽宏大量"]},{"name":"slice","trans":["n. 薄片；部分；菜刀，火铲,vt. 切下；把…分成部分；将…切成薄片,vi. 切开；割破"]},{"name":"humour","trans":["n. 幽默（等于humor）；诙谐,vt. 迁就；使满足"]},{"name":"quality","trans":["n. 质量， 品质；特性；才能,adj. 优质的；高品质的；<英俚>棒极了"]},{"name":"anxious","trans":["adj. 焦虑的；担忧的；渴望的；急切的"]},{"name":"distance","trans":["n. 距离；远方；疏远；间隔,vt. 疏远；把…远远甩在后面"]},{"name":"postpone","trans":["vt. 使…延期；把…放在次要地位；把…放在后面,vi. 延缓，延迟；延缓发作"]},{"name":"ordinary","trans":["adj. 普通的；平凡的；平常的,n. 普通；平常的人（或事）"]},{"name":"scar","trans":["n. 创伤；伤痕,vt. 伤害；给留下伤痕,vi. 结疤；痊愈"]},{"name":"dine","trans":["vi. 进餐，用餐,vt. 宴请"]},{"name":"chum","trans":["n. 室友；密友,vi. 结为密友"]},{"name":"chap","trans":["n. 小伙子；家伙；龟裂,vt. 使皲裂,vi. 皲裂"]},{"name":"fortune","trans":["n. 财富；命运；运气,vt. 给予财富,vi. 偶然发生"]},{"name":"make one's fortune","trans":["发财；发迹，在社会上获得地位"]},{"name":"drag","trans":["n. 拖；拖累,vi. 拖曳；缓慢而吃力地行进,vt. 拖累；拖拉；缓慢而吃力地行进"]},{"name":"ought to","trans":["modalv. 应该；应当；（表示期望或可能发生的事）应该；（表示劝告或建议）应该,v. 应该, 理应；应然；应该要"]},{"name":"destiny","trans":["n. 命运，定数，天命"]},{"name":"correspond","trans":["vi. 符合，一致；相应；通信"]},{"name":"proposition","trans":["n.  命题；提议；主题；议题,vt. 向…提议；向…求欢"]},{"name":"hustle","trans":["n. 推；奔忙；拥挤喧嚷,vt. 催促；猛推；强夺,vi. 赶紧；硬挤过去；骗取财富"]},{"name":"staunch","trans":["adj. 坚定的；忠诚的；坚固的,vt. 止住；止血"]},{"name":"partner","trans":["n. 伙伴；合伙人；配偶,vt. 使合作；与…合伙,vi. 合伙；合股；成为搭档"]},{"name":"turn up","trans":["v. 朝上翻；出现, 开大；找到；露面"]},{"name":"excerpt","trans":["n. 摘录，引用,vt. 引用，摘录,vi. 摘录，引用"]},{"name":"appointed","trans":["v. 任命；指定；约定时间，地点（appoint 的过去分词形式）,adj. 约定的，指定的"]},{"name":"strike","trans":["n. 罢工；打击；殴打,vi. 打，打击；罢工；敲，敲击；抓；打动；穿透,vt. 打，击；罢工；撞击，冲击；侵袭；打动；到达"]},{"name":"cigar","trans":["n. 雪茄"]},{"name":"plain","trans":["n. 平原；无格式；朴实无华的东西,adj. 平的；简单的；朴素的；清晰的,adv. 清楚地；平易地"]},{"name":"scene","trans":["n. 场面；情景；景象；事件"]},{"name":"bitterly","trans":["adv. 苦涩地，悲痛地；残酷地；怨恨地"]},{"name":"ashamed","trans":["adj. 惭愧的，感到难为情的；耻于……的"]},{"name":"unfold","trans":["vi. 展开；显露,vt. 打开；呈现"]},{"name":"location","trans":["n. 位置（形容词locational）；地点；外景拍摄场地"]},{"name":"surroundings","trans":["n. 环境；周围的事物"]},{"name":"personality","trans":["n. 个性；品格；名人"]},{"name":"atmosphere","trans":["n. 气氛；大气；空气"]},{"name":"charity","trans":["n. 慈善；施舍；慈善团体；宽容；施舍物"]},{"name":"monarch","trans":["n. 君主，帝王；最高统治者"]},{"name":"monarch butterfly","trans":["un. 普累克西普班蝶, 帝王蝶；黑脉金斑蝶；帝王斑蝶"]},{"name":"Atlantic","trans":["n. 大西洋,adj. 大西洋的"]},{"name":"whale","trans":["n. 鲸；巨大的东西,vt. 猛揍；使惨败,vi. 捕鲸"]},{"name":"annual","trans":["n. 年刊，年鉴；一年生植物,adj. 年度的；每年的"]},{"name":"migration","trans":["n. 迁移；移民；移动"]},{"name":"migrate","trans":["vi. 移动；随季节而移居；移往,vt. 使移居；使移植"]},{"name":"seek","trans":["vt. 寻求；寻找；探索；搜索,vi. 寻找；探索；搜索"]},{"name":"professor","trans":["n. 教授；教师；公开表示信仰的人"]},{"name":"measure","trans":["n. 测量；措施；程度；尺寸,vt. 测量；估量；权衡,vi. 测量；估量"]},{"name":"position","trans":["n. 位置，方位；职位，工作；姿态；站位,vt. 安置；把……放在适当位置"]},{"name":"determine","trans":["v. （使）下决心，（使）做出决定,vt. 决定，确定；判定，判决；限定,vi. 确定；决定；判决，终止；了结，终止，结束"]},{"name":"eventually","trans":["adv. 最后，终于"]},{"name":"solution","trans":["n. 解决方案；溶液；溶解；解答"]},{"name":"mystery","trans":["n. 秘密，谜；神秘，神秘的事物；推理小说，推理剧；常作 mysteries 秘技，秘诀"]},{"name":"amazing","trans":["adj. 令人惊异的,v. 使吃惊（amaze的ing形式）"]},{"name":"crash","trans":["n. 撞碎；坠毁；破产；轰隆声；睡觉,vi. 摔碎；坠落；发出隆隆声；(金融企业等)破产,vt. 打碎；使坠毁、撞坏；擅自闯入"]},{"name":"per cent","trans":["adj. 每一百中,n. 百分之…, 百分数；百分率；百分比"]},{"name":"destroy","trans":["vt. 破坏；消灭；毁坏"]},{"name":"chemical","trans":["n. 化学制品，化学药品,adj. 化学的"]},{"name":"caterpillar","trans":["adj. 有履带装置的,n.  毛虫；履带车"]},{"name":"creature","trans":["n. 动物，生物；人；创造物"]},{"name":"survive","trans":["vi. 幸存；活下来,vt. 幸存；生还；幸免于；比...活得长"]},{"name":"effect","trans":["n. 影响；效果；作用,vt. 产生；达到目的"]},{"name":"flow chart","trans":["n. 流程图, 流程表单；流程图或过程图；流程图表"]},{"name":"accommodation","trans":["n. 住处，膳宿；调节；和解；预订铺位"]},{"name":"idiom","trans":["n. 成语，习语；土话"]},{"name":"kill two birds with one stone","trans":["na. 一举两得；一石两鸟, 一箭双雕；一石二鸟；一石双鸟"]},{"name":"when the cat's away","trans":[" 情寻猫脚印"]},{"name":"hold your horses","trans":["na. 沉住气, 耐心点儿；勒住你的马；别着急"]},{"name":"rain cats and dogs","trans":["v. 大雨倾盆, 倾盆大雨；下倾盆大雨；瓢泼大雨"]},{"name":"authority","trans":["n. 权威；权力；当局"]},{"name":"source","trans":["n. 来源；水源；原始资料"]},{"name":"found","trans":["v. 找到（find的过去分词）,vt. 创立，建立；创办"]},{"name":"photographer","trans":["n. 摄影师；照相师"]},{"name":"button","trans":["n. 按钮；纽扣,vt. 扣住；扣紧；在…上装纽扣,vi. 扣住；装有纽扣；扣上纽扣"]},{"name":"recover","trans":["n. 还原至预备姿势,vt. 恢复；弥补；重新获得,vi. 恢复；胜诉；重新得球"]},{"name":"shock","trans":["n. 休克；震惊；震动；打击；禾束堆,adj. 浓密的；蓬乱的,vt. 使休克；使震惊；使震动；使受电击；把…堆成禾束堆,vi. 感到震惊；受到震动；堆成禾束堆"]},{"name":"element","trans":["n. 元素；要素；原理；成分；自然环境"]},{"name":"the elements","trans":[" 元素；几何原本；元素周期表"]},{"name":"brave the elements","trans":["顶风冒雨"]},{"name":"variety","trans":["n. 多样；种类；杂耍；变化，多样化"]},{"name":"per","trans":["prep. 每；经；按照；每一"]},{"name":"encounter","trans":["n. 遭遇，偶然碰见,vi. 遭遇；偶然相遇,vt. 遭遇，邂逅；遇到"]},{"name":"path","trans":["n. 道路；小路；轨道"]},{"name":"breathtaking","trans":["adj. 惊人的；惊险的；令人激动的"]},{"name":"eagle","trans":["n. 鹰；鹰状标饰"]},{"name":"concentrate","trans":["n. 浓缩，精选；浓缩液,vi. 集中；浓缩；全神贯注；聚集,vt. 集中；浓缩"]},{"name":"freeze","trans":["n. 冻结；凝固,vt. 使…冻住；使…结冰,vi. 冻结；冷冻；僵硬"]},{"name":"stare","trans":["n. 凝视；注视,vt. 凝视，盯着看,vi. 凝视，盯着看；显眼"]},{"name":"capture","trans":["n. 捕获；战利品，俘虏,vt. 俘获；夺得；捕捉，拍摄,录制"]},{"name":"image","trans":["n. 影像；想象；肖像；偶像,vt. 想象；反映；象征；作…的像"]},{"name":"after all","trans":["na. 毕竟；终究；最后, 究竟；到底；终于"]},{"name":"reaction","trans":["n. 反应，感应；反动，复古；反作用"]},{"name":"file","trans":["n. 文件；档案；文件夹；锉刀,vt. 提出；锉；琢磨；把…归档,vi. 列队行进；用锉刀锉"]},{"name":"wrap","trans":["n. 外套；围巾,vt. 包；缠绕；隐藏；掩护,vi. 包起来；缠绕；穿外衣"]},{"name":"sheet","trans":["n. 薄片，纸张；薄板；床单,adj. 片状的,vt. 覆盖；盖上被单；使成大片,vi. 成片流动；大片落下"]},{"name":"frost","trans":["n. 霜；冰冻，严寒；冷淡,vi. 结霜；受冻,vt. 结霜于；冻坏"]},{"name":"terrace","trans":["n. 平台；梯田；阳台,adj. （女服）叠层式的,vt. 使成梯田，使成阶地；使有平台屋顶,vi. 成阶地；成梯田；筑成坛"]},{"name":"dynasty","trans":["n. 王朝，朝代"]},{"name":"completion","trans":["n. 完成，结束；实现"]},{"name":"region","trans":["n. 地区；范围；部位"]},{"name":"therefore","trans":["adv. 因此；所以"]},{"name":"steep","trans":["n. 峭壁；浸渍,adj. 陡峭的；不合理的；夸大的；急剧升降的,vt. 泡；浸；使…充满,vi. 泡；沉浸"]},{"name":"soil","trans":["n. 土地；土壤；国家；粪便；务农；温床,vt. 弄脏；污辱,vi. 变脏"]},{"name":"shallow","trans":["n.  浅滩,adj. 浅的；肤浅的,vt. 使变浅,vi. 变浅"]},{"name":"prevent","trans":["vt. 预防，防止；阻止,vi. 妨碍，阻止"]},{"name":"harmony","trans":["n. 协调；和睦；融洽；调和"]},{"name":"design","trans":["n. 设计；图案,vt. 设计；计划；构思,vi. 设计"]},{"name":"vapour","trans":["n. 蒸气（等于vapor）；水蒸气"]},{"name":"harm","trans":["n. 伤害；损害,vt. 伤害；危害；损害"]},{"name":"crop","trans":["n. 产量；农作物；庄稼；平头,vt. 种植；收割；修剪；剪短,vi. 收获"]},{"name":"agriculture","trans":["n. 农业；农耕；农业生产；农艺，农学"]},{"name":"replace","trans":["vt. 取代，代替；替换，更换；归还，偿还；把…放回原处"]},{"name":"material","trans":["adj. 重要的；物质的，实质性的；肉体的,n. 材料，原料；物资；布料"]},{"name":"mineral","trans":["n. 矿物；（英）矿泉水；无机物；苏打水（常用复数表示）,adj. 矿物的；矿质的"]},{"name":"consumer","trans":["n. 消费者；用户，顾客"]},{"name":"priority","trans":["n. 优先；优先权； 优先次序；优先考虑的事"]},{"name":"beauty","trans":["n. 美；美丽；美人；美好的东西"]},{"name":"barrier","trans":["n. 障碍物，屏障；界线,vt. 把…关入栅栏"]},{"name":"reef","trans":["n. 暗礁； 矿脉；收帆,vt. 收帆；缩帆,vi. 缩帆；收帆"]},{"name":"structure","trans":["n. 结构；构造；建筑物,vt. 组织；构成；建造"]},{"name":"living","trans":["adj. 活的；现存的；活跃的；逼真的,n. 生活；生存；生计,v. 生活；居住（live的ing形式）；度过"]},{"name":"organism","trans":["n. 有机体；生物体；微生物"]},{"name":"observatory","trans":["n. 天文台；气象台；瞭望台"]},{"name":"basin","trans":["n. 水池；流域；盆地；盆"]},{"name":"grand","trans":["n. 大钢琴；一千美元,adj. 宏伟的；豪华的；极重要的"]},{"name":"canyon","trans":["n. 峡谷"]},{"name":"valley","trans":["n. 山谷；流域；溪谷"]},{"name":"narrow","trans":["adj. 狭窄的，有限的；勉强的；精密的；度量小的,n. 海峡；狭窄部分，隘路,vt. 使变狭窄,vi. 变窄"]},{"name":"platform","trans":["n. 平台；月台，站台；坛；讲台"]},{"name":"waterfall","trans":["n. 瀑布；瀑布似的东西"]},{"name":"thunder","trans":["n. 雷；轰隆声；恐吓,vt. 轰隆地发出；大声喊出,vi. 打雷；怒喝"]},{"name":"channel","trans":["n. 通道；频道；海峡,vt. 引导，开导；形成河道"]},{"name":"tunnel","trans":["n. 隧道；坑道；洞穴通道,vt. 挖；在…打开通道；在…挖掘隧道,vi. 挖掘隧道；打开通道"]},{"name":"camel","trans":["n.  骆驼；打捞浮筒；工作作风官僚,adj. 驼色的；暗棕色的,vi. 工作刻板平庸"]},{"name":"desert","trans":["n. 沙漠；荒原；应得的赏罚,vt. 遗弃；放弃；逃跑,adj. 沙漠的；荒凉的；不毛的,vi. 遗弃；开小差；逃掉"]},{"name":"sail","trans":["n. 帆，篷；航行,vi. 航行；启航，开船,vt. 航行"]},{"name":"climate","trans":["n. 气候；风气；思潮；风土"]},{"name":"inside","trans":["prep. 少于；在…之内,n. 里面；内部；内情；内脏,adj. 里面的；内部的；秘密的,adv. 在里面"]},{"name":"publish","trans":["vi. 出版；发行；刊印,vt. 出版；发表；公布"]},{"name":"green fingers","trans":["n. 园艺技能；种植技能, 绿手指；有园艺技能；园艺能手"]},{"name":"sunflower","trans":["n. 向日葵"]},{"name":"expert","trans":["n. 专家；行家；能手,adj. 熟练的；内行的；老练的,vt. 当专家；在…中当行家"]},{"name":"branch","trans":["n. 树枝，分枝；分部；支流,vt. 分支；出现分歧,vi. 分支；出现分歧"]},{"name":"rent","trans":["n. 租金,vt. 出租；租用；租借,vi. 租；出租"]},{"name":"rooftop","trans":["n. 屋顶,adj. 屋顶上的"]},{"name":"thistle","trans":["n.  蓟"]},{"name":"limited","trans":["adj. 有限的,n. 高级快车"]},{"name":"benefit","trans":["n. 利益，好处；救济金,vt. 有益于，对…有益,vi. 受益，得益"]},{"name":"herb","trans":["n. 香草，药草"]},{"name":"pleasant","trans":["adj. 令人愉快的，舒适的；讨人喜欢的，和蔼可亲的"]},{"name":"flavour","trans":["n. 香味；滋味,vt. 给……调味；给……增添风趣"]},{"name":"energy","trans":["n.  能量；精力；活力；精神"]},{"name":"system","trans":["n. 制度，体制；系统；方法"]}]