[{"name":"when","trans":["conj. 考虑到；既然；当…时；在…时；如果,n. 时间，时候；日期；场合,adv. 什么时候，何时；（用于时间的表达方式之后）在那时；其时；当时,pron. 那时；什么时侯"]},{"name":"month","trans":["n. 月，一个月的时间"]},{"name":"January","trans":["n. 一月"]},{"name":"February","trans":["n. 二月"]},{"name":"March","trans":["找不到解释"]},{"name":"April","trans":["n. 四月"]},{"name":"May","trans":["找不到解释"]},{"name":"June","trans":["n. 六月；琼（人名，来源于拉丁语，含义是“年轻气盛的六月”）"]},{"name":"July","trans":["n. 七月"]},{"name":"August","trans":["找不到解释"]},{"name":"September","trans":["n. 九月"]},{"name":"October","trans":["n.  十月"]},{"name":"November","trans":["n. 十一月"]},{"name":"December","trans":["n. 十二月"]},{"name":"happy","trans":["adj. 幸福的；高兴的；巧妙的"]},{"name":"Happy birthday!","trans":["找不到解释"]},{"name":"old","trans":["adj. 陈旧的，古老的；年老的,n. 古时"]},{"name":"How old ...?","trans":["找不到解释"]},{"name":"party","trans":["n. 政党，党派；聚会，派对；当事人 ,vi. 参加社交聚会 "]},{"name":"see","trans":["vi. 看；看见；领会,vt. 看见；理解；领会"]},{"name":"See you!","trans":["再见!"]},{"name":"first","trans":["num. 第一,n. 第一；开始；冠军,adj. 第一的；基本的；最早的,adv. 第一；首先；优先；宁愿"]},{"name":"second","trans":["num. 第二,n. 秒；第二名；瞬间；二等品,adj. 第二的；次要的；附加的,vt. 支持,adv. 第二；其次；居第二位"]},{"name":"third","trans":["num. 第三；三分之一,adj. 第三的；三分之一的"]},{"name":"fifth","trans":["num. 第五,n. 第五；五分之一,adj. 第五的；五分之一的"]},{"name":"eighth","trans":["num. 第八；八分之一,adj. 第八的；八分之一的"]},{"name":"ninth","trans":["num. 第九,adj. 第九的；九分之一的,n. 九分之一"]},{"name":"twelfth","trans":["n. 第十二；月的第十二日,adj. 第十二的，第十二个的；十二分之一的"]},{"name":"twentieth","trans":["n. 二十分之一,num. 第二十,adj. 第二十的；二十分之一的"]},{"name":"test","trans":["n. 试验；检验,vt. 试验；测试,vi. 试验；测试"]},{"name":"trip","trans":["n. 旅行；绊倒；差错,vt. 绊倒；使犯错,vi. 绊倒；远足；犯错误；轻快地走"]},{"name":"art","trans":["n. 艺术；美术；艺术品,v. 是（be的变体）,adj. 艺术的；艺术品的"]},{"name":"festival","trans":["n. 节日；庆祝，纪念活动；欢乐,adj. 节日的，喜庆的；快乐的"]},{"name":"dear","trans":["n. 亲爱的人,adj. 亲爱的；尊敬的；昂贵的,adv. 高价地；疼爱地,int. 哎呀"]},{"name":"student","trans":["n. 学生；学者"]},{"name":"thing","trans":["n. 事情；东西；事物；情况"]},{"name":"term","trans":["n. 术语；学期；期限；条款；(代数式等的)项,vt. 把…叫做"]},{"name":"busy","trans":["adj. 忙碌的；热闹的；正被占用的,vt. 使忙于"]},{"name":"time","trans":["n. 时间；时代；次数；节拍；倍数,adj. 定时的；定期的；分期的,vt. 计时；测定…的时间；安排…的速度"]},{"name":"Have a good time!","trans":["找不到解释"]},{"name":"there","trans":["n. 那个地方,adv. 在那里；在那边；在那点上,int. 你瞧"]},{"name":"favorite","trans":["n. 幸运儿；喜欢的事物；特别喜欢的人,adj. 最喜爱的；中意的；宠爱的"]},{"name":"favourite","trans":["n. 特别喜爱的人（或物）,adj. 特别受喜爱的"]},{"name":"subject","trans":["n. 主题；科目； 主语；国民,adj. 服从的；易患…的；受制于…的,vt. 使…隶属；使屈从于…"]},{"name":"science","trans":["n. 科学；技术；学科；理科"]},{"name":"P.E.","trans":["找不到解释"]},{"name":"physical education","trans":["n. 体育教学, 体育教育；体育课；物理教育"]},{"name":"music","trans":["n. 音乐，乐曲"]},{"name":"math","trans":["n. 数学（等于mathematics）"]},{"name":"Chinese","trans":["n. 中文，汉语；中国人,adj. 中国的，中国人的；中国话的"]},{"name":"geography","trans":["n. 地理；地形"]},{"name":"history","trans":["n. 历史，历史学；历史记录；来历"]},{"name":"why","trans":["int. 哎呀！什么？,adv. 为什么"]},{"name":"because","trans":["conj. 因为"]},{"name":"Monday","trans":["n. 星期一"]},{"name":"Friday","trans":["n. 星期五"]},{"name":"Saturday","trans":["n. 星期六"]},{"name":"for sure","trans":["adv. 确实, 肯定地；确切地；毫无疑问"]},{"name":"free","trans":["adj. 免费的；自由的，不受约束的； 游离的,vt. 使自由，解放；释放,adv. 自由地；免费"]},{"name":"cool","trans":["n. 凉爽；凉爽的空气,adj. 凉爽的；冷静的；出色的,vt. 使…冷却；使…平静下来,vi. 变凉；平息,adv. 冷静地"]},{"name":"Tuesday","trans":["n. 星期二"]},{"name":"Wednesday","trans":["n. 星期三"]},{"name":"Thursday","trans":["n. 星期四"]},{"name":"Sunday","trans":["n. 星期日；礼拜日"]},{"name":"A.M.","trans":["找不到解释"]},{"name":"a.m.","trans":["abbr. 上午，午前（ante meridiem）"]},{"name":"P.M.","trans":["abbr. 下午（post meridiem）"]},{"name":"p.m.","trans":["找不到解释"]},{"name":"say","trans":["vt. 讲；说明；例如；声称；假设；指明,vi. 讲；表示；念；假定；背诵"]},{"name":"useful","trans":["adj. 有用的，有益的；有帮助的"]},{"name":"from","trans":["prep. 来自，从；由于；今后"]},{"name":"from ... to ...","trans":[" 从到；从什么到什么；起止时间"]},{"name":"Mrs.","trans":["找不到解释"]},{"name":"finish","trans":["n. 结束；完美；回味（葡萄酒）,vt. 完成；结束；用完,vi. 结束，终止；终结"]},{"name":"lesson","trans":["n. 教训；课,vt. 教训；上课"]},{"name":"hour","trans":["n. 小时；钟头；课时；…点钟"]},{"name":"guitar","trans":["n. 吉他，六弦琴,vi. 弹吉他"]},{"name":"sing","trans":["n. 演唱；鸣声；呼啸声,vt. 唱；用诗赞颂；唱着使,vi. 唱歌；歌颂；鸣叫；呼号"]},{"name":"swim","trans":["n. 游泳；漂浮；眩晕,adj. 游泳时穿戴的,vi. 游泳；漂浮；浸；眩晕,vt. 游过；使浮起"]},{"name":"dance","trans":["n. 舞蹈；舞会；舞曲,adj. 舞蹈的；用于跳舞的,vt. 跳舞；使跳跃,vi. 跳舞；跳跃；飘扬"]},{"name":"draw","trans":["n. 平局；抽签,vi. 拉；拖,vt. 画；拉；吸引"]},{"name":"chess","trans":["n. 国际象棋，西洋棋"]},{"name":"play chess","trans":["na. 下象棋, 下棋；下国际象棋；着棋"]},{"name":"speak","trans":["vi. 说话；演讲；表明；陈述,vt. 讲话；发言；讲演"]},{"name":"speak English","trans":["找不到解释"]},{"name":"join","trans":["vt. 参加；结合；连接,vi. 加入；参加；结合,n. 结合；连接；接合点"]},{"name":"club","trans":["n. 俱乐部，社团；夜总会；棍棒；（扑克牌中的）梅花,adj. 俱乐部的,vt. 用棍棒打；募集,vi. 集资；组成俱乐部"]},{"name":"be good at ...","trans":["找不到解释"]},{"name":"tell","trans":["vt. 告诉，说；辨别；吩咐；断定,vi. 讲述；告发，泄密；识别"]},{"name":"story","trans":["n. 故事；小说；新闻报道；来历；假话,vt. 用历史故事画装饰,vi. 说谎"]},{"name":"write","trans":["vi. 写，写字；写作，作曲；写信,vt. 写，书写；写信给；著述"]},{"name":"show","trans":["n. 显示；表演；炫耀,vt. 显示；说明；演出；展出,vi. 显示；说明；指示"]},{"name":"or","trans":["conj. 或，或者；还是"]},{"name":"talk","trans":["n. 谈话；演讲；空谈,vi. 谈话；说闲话,vt. 说；谈话；讨论"]},{"name":"talk to ...","trans":["找不到解释"]},{"name":"kung fu","trans":["n. 功夫（中国拳术）,v. 用功夫击打(对手), 中国功夫；功夫片；徒手功夫"]},{"name":"drum","trans":["n. 鼓；鼓声,vi. 击鼓；大力争取,vt. 击鼓；大力争取"]},{"name":"play the drums","trans":["找不到解释"]},{"name":"piano","trans":["n. 钢琴"]},{"name":"play the piano","trans":["na. 弹钢琴, 演奏钢琴；弹琴；弹钢琴搭配"]},{"name":"violin","trans":["n. 小提琴；小提琴手"]},{"name":"play the violin","trans":[" 拉小提琴；弹小提琴；演奏小提琴"]},{"name":"also","trans":["conj. 并且；另外,adv. 也；而且；同样"]},{"name":"people","trans":["n. 人；人类；民族；公民,vt. 居住于；使住满人"]},{"name":"home","trans":["n. 家，住宅；产地；家乡；避难所,adj. 国内的，家庭的；有效的,vt. 归巢，回家,adv. 在家，回家；深入地"]},{"name":"be good with ...","trans":["找不到解释"]},{"name":"make","trans":["vt. 使得；进行；布置，准备，整理；制造；认为；获得；形成；安排；引起；构成,vi. 开始；前进；增大；被制造,n. 制造；构造；性情"]},{"name":"make friends","trans":[" 交朋友；交友；结交朋友"]},{"name":"today","trans":["n. 今天；现今,adv. 今天；现今"]},{"name":"help with sth.","trans":["找不到解释"]},{"name":"help sb. with sth.","trans":["找不到解释"]},{"name":"center","trans":["n. 中心，中央；中锋；中心点,adj. 中央的，位在正中的,vt. 集中，使聚集在一点；定中心,vi. 居中，被置于中心"]},{"name":"centre","trans":["n. 中心,adj. 中央的,vt. 集中；将…放在中央,vi. 以…为中心"]},{"name":"weekend","trans":["n. 周末，周末休假；周末聚会,adj. 周末的，周末用的,vi. 度周末"]},{"name":"on the weekend","trans":[" 在周末；在这个周末；美式英语"]},{"name":"teach","trans":["vt. 教；教授；教导,vi. 教授；讲授；当老师"]},{"name":"musician","trans":["n. 音乐家"]},{"name":"Lisa","trans":["找不到解释"]},{"name":"Jill","trans":["n. 少女；情人"]},{"name":"Peter","trans":["找不到解释"]},{"name":"up","trans":["prep. 在…之上；向…的较高处,n. 上升；繁荣,adj. 涨的；起床的；向上的,adv. 起来；上涨；向上"]},{"name":"get up","trans":["na. 起床；起身；站起来；叫…起床, 起立；打扮；安排"]},{"name":"dress","trans":["n. 连衣裙；女装,vt. 给…穿衣,vi. 穿衣"]},{"name":"get dressed","trans":["v. 穿衣服, 穿好衣服；穿上衣服；打扮"]},{"name":"brush","trans":["n. 刷子；画笔；毛笔；争吵；与某人有效冲突；灌木丛地带；矮树丛；狐狸尾巴,vi. 刷；擦过；掠过；（经过时）轻触,vt. 刷；画；"]},{"name":"tooth","trans":["n. 牙齿,vt. 给……装齿,vi. 啮合"]},{"name":"shower","trans":["n. 淋浴；（倾泻般出现的）一阵，一大批；阵雨,vt. 大量地给予；把……弄湿,vi. 淋浴；下阵雨"]},{"name":"take a shower","trans":["v. 洗个淋浴, 洗澡；洗淋浴；洗个澡"]},{"name":"usually","trans":["adv. 通常，经常"]},{"name":"forty","trans":["n. 四十,adj. 四十的；四十个的"]},{"name":"wow","trans":["n. 极大的成功；一鸣惊人之举；魔兽世界(World of Warcraft)；失真,int. （表示极大的惊奇或钦佩）哇，呀"]},{"name":"never","trans":["adv. 从未；决不"]},{"name":"early","trans":["adj. 早期的；早熟的,adv. 提早；在初期"]},{"name":"fifty","trans":["n. 五十；五十个；编号为50的东西,adj. 五十的；五十个的；众多的"]},{"name":"job","trans":["n. 工作；职业,vt. 承包；代客买卖,vi. 做零工"]},{"name":"work","trans":["n. 工作； 功；产品；操作；职业；行为；事业；工厂；著作；文学、音乐或艺术作品,vt. 使工作；操作；经营；使缓慢前进,vi. 工作；运作；起作用"]},{"name":"station","trans":["n. 车站；驻地；地位；身份,vt. 配置；安置；驻扎"]},{"name":"radio station","trans":["na. 广播电台, 无线电台；广播站；广播台"]},{"name":"o'clock","trans":["abbr. …点钟（等于of the clock）"]},{"name":"night","trans":["n. 夜晚，晚上；黑暗，黑夜,adj. 夜晚的，夜间的"]},{"name":"funny","trans":["n. 滑稽人物；笑话，有趣的故事；滑稽连环漫画栏；（英）（比赛用）单人双桨小艇,adj. 有趣的，好笑的，滑稽的；（口）稀奇的，古怪的，奇异的；有病的，不舒服的；狡猾的，欺骗（性）的，可疑的，不光明"]},{"name":"exercise","trans":["n. 运动；练习；运用；操练；礼拜；典礼,vt. 锻炼；练习；使用；使忙碌；使惊恐,vi. 运动；练习"]},{"name":"on weekends","trans":[" 在周末；每逢周末；每周末"]},{"name":"best","trans":["n. 最好的人，最好的事物；最佳状态,adj. 最好的,vt. 打败，胜过,adv. 最好地"]},{"name":"group","trans":["n. 组；团体,adj. 群的；团体的,vt. 把…聚集；把…分组,vi. 聚合"]},{"name":"half","trans":["n. 一半；半场；半学年,adj. 一半的；不完全的；半途的,adv. 一半地；部分地"]},{"name":"past","trans":["n. 过去；往事,prep. 越过；晚于,adj. 过去的；结束的,adv. 过；经过"]},{"name":"quarter","trans":["num. 四分之一,n. 四分之一；地区；季度；一刻钟；两角五分；节,vt. 将…四等分；供某人住宿,vi. 住宿；驻扎"]},{"name":"homework","trans":["n. 家庭作业，课外作业"]},{"name":"do homework","trans":[" 做作业；做家庭作业；做功课"]},{"name":"do one's homework","trans":["na. 做功课, 做作业；做家庭作业；的家庭作业"]},{"name":"run","trans":["n. 奔跑；赛跑；趋向；奔跑的路程,vt. 管理，经营；运行；参赛,vi. 经营；奔跑；运转"]},{"name":"clean","trans":["n. 打扫,adj. 清洁的，干净的；清白的,vt. 使干净,vi. 打扫，清扫,adv. 完全地"]},{"name":"walk","trans":["n. 步行，走；散步,vi. 走，步行；散步,vt. 散步；走过"]},{"name":"take a walk","trans":["na. 散步, 散散步；去散步；音乐漫步"]},{"name":"quickly","trans":["adv. 迅速地；很快地"]},{"name":"either","trans":["conj. 也（用于否定句或否定词组后）；根本,prep. 任何一个,adj. 两者之中任一的；两者之中每一的,pron. 任一，两方，随便哪一个；两者中的一个或另一个"]},{"name":"either ... or ...","trans":["找不到解释"]},{"name":"lot","trans":["n. 份额；许多；命运；阄,adv. （与形容词和副词连用）很，非常；（与动词连用）非常,pron. 大量，许多,vt. 分组，把…划分（常与out连用）；把（土地）划分成块,vi. 抽签，拈阄"]},{"name":"lots of","trans":["adj. 许多；很多, 大量；大量的；许多的"]},{"name":"sometimes","trans":["adv. 有时，间或"]},{"name":"taste","trans":["n. 味道；品味；审美,vt. 尝；体验,vi. 尝起来；有…的味道"]},{"name":"life","trans":["n. 生活，生存；寿命"]},{"name":"Rick","trans":["找不到解释"]},{"name":"Jim","trans":["找不到解释"]},{"name":"Scott","trans":["找不到解释"]},{"name":"Tony","trans":["找不到解释"]},{"name":"train","trans":["n. 火车；行列；长队；裙裾,v. 培养；训练；瞄准"]},{"name":"bus","trans":["n. 公共汽车,乘公共汽车"]},{"name":"subway","trans":["n. 地铁；地道,vi. 乘地铁"]},{"name":"take the subway","trans":[" 乘地铁；乘坐地铁；搭地铁"]},{"name":"ride","trans":["n. 骑；乘坐；交通工具；可供骑行的路；（乘坐汽车等的）旅行；乘骑；（乘车或骑车的）短途旅程；供乘骑的游乐设施,vi. 骑马；乘车；依靠；漂浮,vt. 骑；乘；控制；（骑马、自行车等）穿越；搭乘；飘浮"]},{"name":"ride a bike","trans":[" 骑自行车；骑车；骑单车"]},{"name":"sixty","trans":["num. 六十；六十个"]},{"name":"seventy","trans":["n. 七十；七十个；七十岁；七十年代,num. 七十,adj. 七十的；七十个的；七十岁的"]},{"name":"eighty","trans":["num. 八十,n. 八十；八十岁；八十年代,adj. 八十的，八十个的；八十岁的"]},{"name":"ninety","trans":["n. 九十,adj. 九十的；九十岁的,num. 九十"]},{"name":"hundred","trans":["num. 百；百个,n. 一百；许多,adj. 一百的；许多的"]},{"name":"minute","trans":["n. 分，分钟；片刻，一会儿；备忘录，笔记；会议记录,vt. 将…记录下来,adj. 微小的，详细的 "]},{"name":"far","trans":["n. 远方,adj. 远的；久远的,adv. 很；遥远地；久远地；到很远的距离；到很深的程度"]},{"name":"kilometer","trans":["n.  公里； 千米（等于kilometre）"]},{"name":"kilometre","trans":["n.  公里； 千米"]},{"name":"new","trans":["adj. 新的，新鲜的；更新的；初见的,adv. 新近"]},{"name":"every","trans":["adj. 每一的，每个的；每隔…的"]},{"name":"every day","trans":["na. 每日, 每天；每一天；天天"]},{"name":"by","trans":["prep. 通过；被；依据；经由；在附近；在……之前,adv. 通过；经过；附近； 白俄罗斯的国家代码顶级域名"]},{"name":"by bike","trans":[" 骑自行车；骑车；骑单车"]},{"name":"drive","trans":["n. 驱动器；驾车； 内驱力，推进力；快车道,vi. 开车；猛击；飞跑,vt. 推动，发动（机器等）；驾驶（马车，汽车等）；驱赶"]},{"name":"car","trans":["n. 汽车；车厢"]},{"name":"live","trans":["adj. 活的；生动的；实况转播的；精力充沛的,vt. 经历；度过,vi. 活；居住；生存"]},{"name":"stop","trans":["n. 停止；车站；障碍；逗留,vi. 停止；中止；逗留；被塞住,vt. 停止；堵塞；断绝"]},{"name":"think of","trans":["na. 想起, 考虑；认为；想到"]},{"name":"cross","trans":["n. 交叉，十字；十字架，十字形物,adj. 交叉的，相反的；乖戾的；生气的,vt. 杂交；渡过；使相交,vi. 交叉；杂交；横过"]},{"name":"river","trans":["n. 河，江"]},{"name":"many","trans":["pron. 许多；许多人,adj. 许多的"]},{"name":"village","trans":["n. 村庄；村民；（动物的）群落"]},{"name":"between","trans":["prep. 在…之间,adv. 在中间"]},{"name":"between ... and ...","trans":["找不到解释"]},{"name":"bridge","trans":["n. 桥；桥牌；桥接器；船桥,vt. 架桥；渡过"]},{"name":"boat","trans":["n. 小船；轮船,vi. 划船"]},{"name":"ropeway","trans":["n. 索道，空中缆索"]},{"name":"year","trans":["n. 年；年度；历年；年纪；一年的期间；某年级的学生"]},{"name":"afraid","trans":["adj. 害怕的；恐怕；担心的"]},{"name":"like","trans":["vt. 喜欢；想；愿意,vi. 喜欢；希望,prep. 像；如同,adj. 同样的；相似的,n. 爱好；同样的人或物,adv. 可能,conj. 好像"]},{"name":"villager","trans":["n. 乡村居民，村民"]},{"name":"leave","trans":["vt. 离开；留下；遗忘；委托,vi. 离开，出发；留下,n. 许可，同意；休假"]},{"name":"dream","trans":["n. 梦想，愿望；梦,adj. 梦的；理想的；不切实际的,vt. 梦想；做梦；想到,vi. 梦想；做梦，梦见；想到"]},{"name":"true","trans":["n. 真实；准确,adj. 真实的；正确的,vt. 装准,adv. 真实地；准确地"]},{"name":"come true","trans":["na. (预言等)成事实；实现；(作物)不变种地发芽生长, 成为现实；成为事实；变成现实"]},{"name":"Dave","trans":["找不到解释"]},{"name":"rule","trans":["n. 统治；规则,vt. 统治；规定；管理；裁决；支配,vi. 统治；管辖；裁定"]},{"name":"arrive","trans":["vi. 到达；成功；达成；出生"]},{"name":"on time","trans":["na. 按时；及时, 准时；正点；准时地"]},{"name":"be on time","trans":[" 要准时；守时；准时到达"]},{"name":"hallway","trans":["n. 走廊；门厅；玄关"]},{"name":"hall","trans":["n. 过道，门厅，走廊；会堂；食堂；学生宿舍；大厅，前厅；娱乐中心，会所"]},{"name":"dining","trans":["n. 吃饭，进餐,v. 吃饭（dine的现在分词）"]},{"name":"listen","trans":["vi. 听，倾听；听从，听信,n. 听，倾听"]},{"name":"listen to ...","trans":["找不到解释"]},{"name":"fight","trans":["n. 打架；战斗，斗志,vi. 打架；与…打仗，与…斗争；反对…提案"]},{"name":"sorry","trans":["adj. 遗憾的；对不起的，抱歉的,int. 对不起，抱歉（表示委婉的拒绝等）"]},{"name":"outside","trans":["adj. 外面的，外部的；外来的,n. 外部；外观,adv. 在外面，向外面；在室外,prep. 在…范围之外"]},{"name":"wear","trans":["n. 衣物；磨损；耐久性,v. 穿着；用旧；耗损；面露"]},{"name":"important","trans":["adj. 重要的，重大的；有地位的；有权力的"]},{"name":"bring","trans":["vt. 带来；促使；引起；使某人处于某种情况或境地"]},{"name":"uniform","trans":["n. 制服,adj. 统一的；一致的；相同的；均衡的；始终如一的,vt. 使穿制服；使成一样"]},{"name":"quiet","trans":["n. 安静；和平,adj. 安静的；安定的；不动的；温顺的,vt. 使平息；安慰,vi. 平静下来"]},{"name":"out","trans":["adv. 出现；在外；出局；出声地；不流行地,adj. 外面的；出局的；下台的,n. 出局,prep. 向；离去,vi. 出来；暴露,vt. 使熄灭；驱逐"]},{"name":"go out","trans":["na. 出去；灭；辞职；下台, 熄灭；外出；过时"]},{"name":"practice","trans":["n. 实践；练习；惯例,vt. 练习；实习；实行,vi. 练习；实习；实行"]},{"name":"dish","trans":["n. 盘；餐具；一盘食物；外貌有吸引力的人,vt. 盛于碟盘中；分发；使某人的希望破灭；说（某人）的闲话,vi. 成碟状；闲谈"]},{"name":"do the dishes","trans":["na. 洗碗碟, 洗餐具；洗盘子；把盘子洗了"]},{"name":"before","trans":["prep. 在…之前，先于,conj. 在…以前；在…之前,adv. 以前；在前"]},{"name":"make one's bed","trans":["na. 自作自受, 整理床铺；铺床；收拾床铺"]},{"name":"dirty","trans":["adj. 下流的，卑鄙的；肮脏的；恶劣的；暗淡的,vt. 弄脏,vi. 变脏"]},{"name":"kitchen","trans":["n. 厨房；炊具；炊事人员"]},{"name":"more","trans":["adv. 更多；此外；更大程度地,adj. 更多的；附加的,pron. 更多的数量,n. 更多"]},{"name":"noisy","trans":["adj. .嘈杂的；喧闹的；聒噪的"]},{"name":"relax","trans":["vi. 放松，休息；松懈，松弛；变从容；休养,vt. 放松；使休息；使松弛；缓和；使松懈"]},{"name":"read","trans":["n. 阅读；读物,adj. 有学问的,vi. 读；读起来,vt. 阅读；读懂，理解"]},{"name":"terrible","trans":["adj. 可怕的；很糟的；令人讨厌的,adv. 很，非常"]},{"name":"feel","trans":["n. 感觉；触摸,vi. 觉得；摸索,vt. 感觉；认为；触摸；试探"]},{"name":"strict","trans":["adj. 严格的；绝对的；精确的；详细的"]},{"name":"be strict","trans":[" 严格；严厉；是严格的"]},{"name":"be strict with sb.","trans":["找不到解释"]},{"name":"remember","trans":["vi. 记得，记起,vt. 记得；牢记；纪念；代…问好"]},{"name":"follow","trans":["n. 跟随；追随,vi. 跟随；接着,vt. 跟随；遵循；追求；密切注意，注视；注意；倾听"]},{"name":"follow the rules","trans":["找不到解释"]},{"name":"luck","trans":["n. 运气；幸运；带来好运的东西,vi. 靠运气，走运；凑巧碰上"]},{"name":"keep","trans":["vt. 保持；经营；遵守；饲养,vi. 保持；继续不断,n. 保持；生计；生活费"]},{"name":"hair","trans":["n. 头发；毛发；些微,adj. 毛发的；护理毛发的；用毛发制成的,vt. 除去…的毛发,vi. 生长毛发；形成毛状纤维"]},{"name":"learn","trans":["vt. 学习；得知；认识到,vi. 学习；获悉"]},{"name":"Clark","trans":["找不到解释"]},{"name":"Amy","trans":["找不到解释"]},{"name":"Molly","trans":["找不到解释"]},{"name":"New York","trans":["n. 纽约州, 美国纽约；纽约市；纽约步"]},{"name":"panda","trans":["n. 熊猫；猫熊"]},{"name":"zoo","trans":["n. 动物园; <美俚>（铁路货车的最后一节）守车; <美俚>核粒子园"]},{"name":"tiger","trans":["n. 老虎；凶暴的人"]},{"name":"elephant","trans":["n. 象；大号图画纸"]},{"name":"koala","trans":["n. 树袋熊，无尾熊（产于澳大利亚，又名考拉）"]},{"name":"lion","trans":["n. 狮子；名人；勇猛的人；社交场合的名流"]},{"name":"giraffe","trans":["n. 长颈鹿"]},{"name":"animal","trans":["n. 动物,动物的"]},{"name":"cute","trans":["adj. 可爱的；漂亮的；聪明的，伶俐的"]},{"name":"lazy","trans":["adj. 懒惰的；懒洋洋的；怠惰的；慢吞吞的"]},{"name":"smart","trans":["adj. 聪明的；巧妙的；敏捷的；厉害的；潇洒的；剧烈的；时髦的"]},{"name":"beautiful","trans":["adj. 美丽的,出色地,出色的,迷人的,迷人地"]},{"name":"scary","trans":["adj. （事物）可怕的；恐怖的；吓人的；（人）提心吊胆的；引起惊慌的；胆小的"]},{"name":"kind","trans":["n. 种类；性质,adj. 和蔼的；宽容的；令人感激的"]},{"name":"kind of","trans":["na. 有点儿；有几分, 种类；稍微；相当"]},{"name":"Australia","trans":["n. 澳大利亚，澳洲"]},{"name":"south","trans":["n. 南方，南边；南部,adj. 南的，南方的,adv. 在南方，向南方"]},{"name":"Africa","trans":["n. 非洲"]},{"name":"South Africa","trans":["n. 南非；位于非洲南部, 南非共和国；南非地区；南非共和国大使馆"]},{"name":"pet","trans":["n. 宠物；生气；受宠爱的人,adj. 宠爱的,vt. 宠爱,vi. 生气；爱抚"]},{"name":"leg","trans":["n. 腿；支柱"]},{"name":"cat","trans":["n. 猫，猫科动物"]},{"name":"sleep","trans":["n. 睡眠,vi. 睡，睡觉"]},{"name":"friendly","trans":["adj. 友好的；亲切的；支持的；融洽的，和睦的,adv. 友善地；温和地"]},{"name":"shy","trans":["n. 投掷；惊跳,adj. 害羞的；畏缩的，胆怯的,vi. 投；畏缩；惊退；厌恶,vt. 投；乱掷"]},{"name":"save","trans":["prep. 除...之外,n. 救援,vi. 节省；挽救,vt. 节省；保存；储蓄；解救"]},{"name":"symbol","trans":["n. 象征；符号；标志"]},{"name":"flag","trans":["n. 标志；旗子,vt. 标记；插旗,vi. 标记；衰退；枯萎"]},{"name":"forget","trans":["vi. 忘记,vt. 忘记；忽略"]},{"name":"get lost","trans":["int. 滚开；别烦我,v. 迷路；迷失；陷入…而忽略了…, 走开；走失；失踪"]},{"name":"place","trans":["n. 地方；住所；座位,vt. 放置；任命；寄予,vi. 名列前茅；取得名次"]},{"name":"water","trans":["n. 水；海水；雨水；海域，大片的水,vt. 使湿；供以水；给…浇水,vi. 加水；流泪；流口水"]},{"name":"danger","trans":["n. 危险；危险物，威胁"]},{"name":"be in danger","trans":[" 处于危险之中；处于危险中；处于危险当中"]},{"name":"be in great danger","trans":["找不到解释"]},{"name":"cut","trans":["n. 伤口；切口；削减；（服装等的）式样；削球；切入,adj. 割下的；雕过的；缩减的,vt.  切割；削减；缩短；刺痛,vi.  切割；相交；切牌；停拍；不出席"]},{"name":"down","trans":["prep. 沿着，往下,n. 软毛，绒毛； 开阔的高地,adj. 向下的,vt. 打倒，击败,adv. 向下，下去；在下面,vi. 下降；下去"]},{"name":"cut down","trans":["na. 砍倒；削减；减价；夺去…活动力, 减少；缩短；降低"]},{"name":"tree","trans":["n. 树；木料；树状物,vt. 把...赶上树,vi. 爬上树；逃上树"]},{"name":"kill","trans":["vt. 杀死；扼杀；使终止；抵消,vi. 杀死,n. 杀戮；屠杀,adj. 致命的；致死的"]},{"name":"ivory","trans":["n. 象牙；乳白色；长牙,adj. 乳白色的；象牙制的"]},{"name":"over","trans":["adv. 结束；越过；从头到尾,prep. 越过；在…之上；遍于…之上,adj. 结束的；上面的,vt. 越过"]},{"name":"made of","trans":["na. “make certain”的变体, 用……制成的；由…构成；由…造成"]},{"name":"be made of","trans":["na. …制的, 由……制成；用…制成；材料制成"]},{"name":"Julie","trans":["找不到解释"]},{"name":"Becky","trans":["找不到解释"]},{"name":"Thailand","trans":["n. 泰国（东南亚国家名）"]},{"name":"Thai","trans":["n. 泰国人；泰国语,adj. 泰国的；泰国人的"]},{"name":"newspaper","trans":["n. 报纸,报社,旧报纸"]},{"name":"read a newspaper","trans":["找不到解释"]},{"name":"use","trans":["n. 使用；用途；发挥,vt. 利用；耗费,vi. 使用，运用"]},{"name":"soup","trans":["n. 汤，羹；马力,vt. 加速；增加马力"]},{"name":"make soup","trans":["找不到解释"]},{"name":"wash","trans":["n. 洗涤；洗的衣服；化妆水；冲积物,vt. 洗涤；洗刷；冲走；拍打,vi. 洗澡；被冲蚀"]},{"name":"movie","trans":["n. 电影；电影院；电影业,adj. 电影的"]},{"name":"go to the movies","trans":["na. 去看电影, 加S是电影院；看一场电影；哦看电影"]},{"name":"just","trans":["adv. 只是，仅仅；刚才，刚刚；正好，恰好；实在；刚要,adj. 公正的，合理的；正直的，正义的；正确的；公平的；应得的"]},{"name":"eat out","trans":["v. 出去吃；在外面吃饭, 下馆子；出去吃饭；上馆子吃饭"]},{"name":"house","trans":["n. 住宅；家庭；机构；议会；某种用途的建筑物,vt. 覆盖；给…房子住；把…储藏在房内,vi. 住"]},{"name":"drink","trans":["n. 酒，饮料；喝酒,vt. 喝，饮；吸收；举杯庆贺,vi. 喝酒；饮水；干杯"]},{"name":"tea","trans":["n. 茶叶；茶树；茶点,vt. 给…沏茶,vi. 喝茶；进茶点"]},{"name":"drink tea","trans":[" 喝茶；饮茶；品茗尝鲜"]},{"name":"tomorrow","trans":["n. 明天；未来,adv. 明天；未来地（等于to-morrow）"]},{"name":"pool","trans":["n. 联营；撞球；水塘；共同资金,vt. 合伙经营,vi. 联营，合伙经营"]},{"name":"shop","trans":["n. 商店；店铺,vt. 购物,vi. 购物；买东西"]},{"name":"supermarket","trans":["n. 超级市场；自助售货商店"]},{"name":"man","trans":["n. 人；男人；人类；丈夫；雇工,vt. 操纵；给…配置人员；使增强勇气；在…就位"]},{"name":"race","trans":["n. 属，种；种族，人种；家庭，门第,vt. 使参加比赛；和…竞赛；使急走，使全速行进,vi. 比速度，参加竞赛；全速行进"]},{"name":"host","trans":["n.  主机；主人；主持人；许多,vt. 主持；当主人招待,vi. 群集；做主人"]},{"name":"study","trans":["n. 学习，研究；课题；书房；学问,vt. 学习；考虑；攻读；细察,vi. 研究；用功"]},{"name":"state","trans":["n. 国家；州；情形,adj. 国家的；州的；正式的,vt. 规定；声明；陈述"]},{"name":"the United States","trans":["na. 美利坚合众国, 美国；联合国；是美利坚合众国的简称"]},{"name":"America","trans":["n. 美洲（包括北美和南美洲）；美国"]},{"name":"the US","trans":["美国（the United States of America）"]},{"name":"the USA","trans":[" 美国；美利坚合众国；现在我们有美国的大哥"]},{"name":"American","trans":["n. 美国人，美洲人；美国英语,adj. 美国的，美洲的；地道美国式的"]},{"name":"dragon","trans":["n. 龙；凶暴的人，凶恶的人；严厉而有警觉性的女人"]},{"name":"Dragon Boat Festival","trans":["找不到解释"]},{"name":"any","trans":["adj. 任何的；所有的；丝毫,pron. 任何；任何一个；若干,adv. 稍微；少许"]},{"name":"other","trans":["adj. 其他的，另外的,pron. 另外一个"]},{"name":"young","trans":["n. 年轻人；（动物的）崽，仔,adj. 年轻的；初期的；没有经验的"]},{"name":"child","trans":["n. 儿童，小孩，孩子；产物；子孙；幼稚的人；弟子"]},{"name":"children","trans":["n. 孩子们（child的复数）"]},{"name":"miss","trans":["n. 女士，小姐，年轻未婚女子,vt. 错过，想念，缺（勤）"]},{"name":"wish","trans":["n. 希望；祝福；心愿,vt. 祝愿；渴望；向…致问候语,vi. 愿望；需要"]},{"name":"delicious","trans":["adj. 美味的；可口的"]},{"name":"still","trans":["conj. 仍然；但是；尽管如此,n. 寂静；剧照；蒸馏室,adj. 静止的，不动的；寂静的，平静的；不起泡的,adv. 仍然；更；静止地,vt. 蒸馏；使…静止；使…平静下来,vi. 静止；平静；蒸馏"]},{"name":"living","trans":["adj. 活的；现存的；活跃的；逼真的,n. 生活；生存；生计,v. 生活；居住（live的ing形式）；度过"]},{"name":"Steve","trans":["找不到解释"]},{"name":"Laura","trans":["找不到解释"]},{"name":"rain","trans":["n. 雨；下雨；雨天；雨季,vt. 大量地给；使大量落下,vi. 下雨；降雨"]},{"name":"windy","trans":["adj. 多风的，有风的；腹胀的；吹牛的"]},{"name":"cloudy","trans":["adj. 多云的；阴天的；愁容满面的"]},{"name":"sunny","trans":["adj. 阳光充足的，和煦的；快活的；性情开朗的"]},{"name":"snow","trans":["n. 雪，积雪；下雪,vt. 使纷纷落下；使变白,vi. 降雪"]},{"name":"weather","trans":["n. 天气；气象；气候；处境,vt. 经受住；使风化；侵蚀；使受风吹雨打,adj. 露天的；迎风的,vi. 风化；受侵蚀；经受风雨"]},{"name":"cook","trans":["n. 厨师，厨子,vt. 烹调，煮,vi. 烹调，做菜"]},{"name":"bad","trans":["n. 坏事；坏人,adj. 坏的；严重的；劣质的,adv. 很，非常；坏地；邪恶地"]},{"name":"park","trans":["n. 公园； 停车场,vt. 停放；放置；寄存,vi. 停放车辆"]},{"name":"message","trans":["n. 消息；差使；启示；预言；广告词,vi. 报信，报告； 报文,vt. 通知"]},{"name":"take a message","trans":["v. 传话, 捎口信；捎个口信；留言"]},{"name":"him","trans":["pron. 他（宾格）"]},{"name":"he","trans":["n. 男孩，男人；它（雄性动物）,pron. 他"]},{"name":"could","trans":["aux. 能够,v. 能（can的过去式）"]},{"name":"back","trans":["n. 后面；背部；靠背；足球等的后卫；书报等的末尾,adj. 后面的；过去的；拖欠的,vt. 支持；后退；背书；下赌注,adv. 以前；向后地；来回地；上溯；回来；回原处,vi. 后退；背靠；倒退"]},{"name":"call back","trans":["na. 取消；喊回；回一个电话；再打一个电话来, 回电话；收回；回调"]},{"name":"call sb. back","trans":["na. 取消；喊回；回一个电话；再打一个电话来, 回电话；收回；回调"]},{"name":"problem","trans":["n. 难题；引起麻烦的人,adj. 成问题的；难处理的"]},{"name":"again","trans":["adv. 又，此外；再一次；再说；增加,n. （英、保）阿盖恩"]},{"name":"dry","trans":["n. 干涸,adj. 干的；口渴的；枯燥无味的；禁酒的,vt. 把…弄干,vi. 变干"]},{"name":"cold","trans":["n. 寒冷；感冒,adj. 寒冷的；冷淡的，不热情的；失去知觉的,adv. 完全地"]},{"name":"hot","trans":["adj. 热的；辣的；热情的；激动的；紧迫的,vt. 增加；给…加温,adv. 热；紧迫地,vi. 变热"]},{"name":"warm","trans":["n. 取暖；加热,adj. 温暖的；热情的,vt. 使…兴奋；使…温暖；使…感兴趣,vi. 同情；激动；变温暖"]},{"name":"visit","trans":["n. 访问；参观；逗留,vt. 访问；参观；视察,vi. 访问；暂住；闲谈"]},{"name":"Canada","trans":["n. 加拿大（北美洲国家）"]},{"name":"summer","trans":["n. 夏季；全盛时期,adj. 夏季的,vi. 避暑；过夏天"]},{"name":"sit","trans":["vi. 坐；位于,vt. 使就座"]},{"name":"juice","trans":["n. （水果）汁，液；果汁"]},{"name":"soon","trans":["adv. 快；不久，一会儿；立刻；宁愿"]},{"name":"vacation","trans":["n. 假期；（房屋）搬出,vi. 休假，度假"]},{"name":"on a vacation","trans":["找不到解释"]},{"name":"hard","trans":["adj. 努力的；硬的；困难的；辛苦的；确实的；严厉的；猛烈的；冷酷无情的,adv. 努力地；困难地；辛苦地；接近地；猛烈地；牢固地"]},{"name":"Europe","trans":["n. 欧洲"]},{"name":"mountain","trans":["n. 山；山脉"]},{"name":"country","trans":["n. 国家，国土；国民；乡下，农村；乡村；故乡,adj. 祖国的，故乡的；地方的，乡村的；国家的；粗鲁的；乡村音乐的"]},{"name":"skate","trans":["n. 溜冰；冰鞋,vi. 滑冰；滑过"]},{"name":"snowy","trans":["adj. 下雪的，多雪的；被雪覆盖的；洁白无瑕的"]},{"name":"winter","trans":["n. 冬季；年岁；萧条期,adj. 冬天的；越冬的,vi. 过冬"]},{"name":"Russian","trans":["n. 俄语；俄国人,adj. 俄国的；俄语的"]},{"name":"snowman","trans":["n. 雪人"]},{"name":"rainy","trans":["adj. 下雨的；多雨的"]},{"name":"Joe","trans":["找不到解释"]},{"name":"Jeff","trans":["找不到解释"]},{"name":"Moscow","trans":["n. 莫斯科（俄罗斯首都）"]},{"name":"Toronto","trans":["找不到解释"]},{"name":"Boston","trans":["n. 波士顿（美国城市）"]},{"name":"post","trans":["n. 岗位；邮件；标杆,vt. 张贴；公布；邮递；布置,vi. 快速行进"]},{"name":"office","trans":["n. 办公室；政府机关；官职；营业处"]},{"name":"post office","trans":["n. 邮局；邮政部门；邮政系统；邮差敲门游戏（儿童用假托的信件换取亲吻）, 邮政局；邮电局；邮政署"]},{"name":"police","trans":["n. 警察，警方；治安,adj. 警察的；有关警察的,vt. 监督；管辖；维持治安；为…配备警察"]},{"name":"police station","trans":["n. 警察局；派出所, 警局；公安局；警察分局"]},{"name":"hotel","trans":["n. 旅馆，饭店；客栈,vt. 使…在饭店下榻,vi. 进行旅馆式办公"]},{"name":"restaurant","trans":["n. 餐馆； 饭店"]},{"name":"bank","trans":["n. 银行；岸；浅滩；储库,vt. 将…存入银行；倾斜转弯,vi. 堆积；倾斜转弯"]},{"name":"hospital","trans":["n. 医院"]},{"name":"street","trans":["n. 街道,adj. 街道的"]},{"name":"pay","trans":["n. 工资，薪水；付款；报答,vt. 支付，付；偿还，补偿；给予,vi. 付款；偿还,adj. 收费的；需付费的"]},{"name":"pay phone","trans":["na. 公用自动收费电话亭, 公用电话；投币式公用电话；公共电话"]},{"name":"near","trans":["adj. 近的；亲近的；近似的,adv. 近；接近,prep. 靠近；近似于"]},{"name":"across","trans":["prep. 穿过；横穿,adv. 横过；在对面"]},{"name":"across from","trans":["na. 在…的正对面, 在……的对面；在……对面；在……对过"]},{"name":"front","trans":["n. 前面；正面；前线,adj. 前面的；正面的,vt. 面对；朝向；对付,vi. 朝向,adv. 在前面；向前"]},{"name":"in front of","trans":["na. 在…的前面, 在……前面；在……的前面；在…面前"]},{"name":"behind","trans":["prep. 落后于；支持；晚于,n. 屁股,adv. 在后地；在原处"]},{"name":"town","trans":["n. 城镇，市镇；市内商业区"]},{"name":"around","trans":["prep. 四处；在…周围,adv. 大约；到处；在附近"]},{"name":"north","trans":["找不到解释"]},{"name":"along","trans":["prep. 沿着；顺着,adv. 一起；向前；来到"]},{"name":"go along","trans":["na. 前进, 进行；沿着……一直走；同意"]},{"name":"go along the street","trans":["找不到解释"]},{"name":"turn","trans":["n. 转弯；变化；(损害或有益于别人的)行为，举动，举止,vi. 转向；转变；转动,vt. 转动，使旋转；转弯；翻过来；兑换"]},{"name":"right","trans":["n. 正确；右边；正义,adj. 正确的；直接的；右方的,vt. 纠正,adv. 正确地；恰当地；彻底地,vi. 复正；恢复平稳"]},{"name":"left","trans":["adj. 左边的；左派的；剩下的,adv. 在左面,n. 左边；左派；激进分子,v. 离开（leave的过去式）"]},{"name":"turn right","trans":["na. 转往右面, 向右转；向右拐；转右"]},{"name":"turn left","trans":["un. 向左转, 转左；向左走；向左拐"]},{"name":"crossing","trans":["n. 十字路口；杂交；横渡；横道,v. 横越（cross的现在分词）"]},{"name":"neighborhood","trans":["n. 附近；街坊；接近；街区"]},{"name":"spend","trans":["n. 预算,vt. 度过，消磨（时光）；花费；浪费；用尽,vi. 花钱；用尽，耗尽"]},{"name":"spend time","trans":[" 度过时光；花时间；消磨时间"]},{"name":"climb","trans":["n. 爬；攀登,vi. 爬；攀登；上升,vt. 爬；攀登；上升"]},{"name":"road","trans":["n. 公路，马路；道路；手段,adj. （美）巡回的,vt. （狗）沿臭迹追逐（猎物）"]},{"name":"often","trans":["adv. 常常，时常"]},{"name":"air","trans":["n. 空气，大气；天空；样子；曲调,vt. 使通风，晾干；夸耀,vi. 通风"]},{"name":"sunshine","trans":["n. 阳光；愉快；晴天；快活"]},{"name":"free","trans":["adj. 免费的；自由的，不受约束的； 游离的,vt. 使自由，解放；释放,adv. 自由地；免费"]},{"name":"enjoy","trans":["vt. 欣赏，享受；喜爱；使过得快活"]},{"name":"enjoy reading","trans":["找不到解释"]},{"name":"easily","trans":["adv. 容易地；无疑地"]},{"name":"money","trans":["n. 钱；货币；财富"]}]